{"BR-135":{"0":{"CHI0G12":null},"1001":{"CHI0G12":{"Aceleração":0.005027777777777468,"Acima da Velocidade":false,"Batido":false,"Posicao":[565.0,611.0999999999997],"Posição Prevista":3553.3499999998685,"Risco Colisão":[],"Tempo de Execução":187,"Velocidade":1.0066666666666606}},"1017":{"CHI0G12":{"Aceleração":-0.0031510416666660213,"Acima da Velocidade":false,"Batido":false,"Posicao":[565.0,626.3999999999997],"Posição Prevista":92.40000000030113,"Risco Colisão":[],"Tempo de Execução":187,"Velocidade":0.9562500000000043}},"1033":{"CHI0G12":{"Aceleração":0.0007812499999997335,"Acima da Velocidade":false,"Batido":false,"Posicao":[565.0,641.8999999999997],"Posição Prevista":1931.8999999998769,"Risco Colisão":[],"Tempo de Execução":187,"Velocidade":0.96875}},"1049":{"CHI0G12":{"Aceleração":0.0007812499999997335,"Acima da Velocidade":false,"Batido":false,"Posicao":[565.0,657.5999999999997],"Posição Prevista":1959.5999999998728,"Risco Colisão":[],"Tempo de Execução":187,"Velocidade":0.9812499999999957}},"1065":{"CHI0G12":{"Aceleração":0.0007812500000001776,"Acima da Velocidade":false,"Batido":false,"Posicao":[565.0,673.4999999999997],"Posição Prevista":1987.50000000008,"Risco Colisão":[],"Tempo de Execução":187,"Velocidade":0.9937499999999986}},"1081":{"CHI0G12":{"Aceleração":0.0007812500000001776,"Acima da Velocidade":false,"Batido":false,"Posicao":[565.0,689.5999999999997],"Posição Prevista":2015.600000000083,"Risco Colisão":[],"Tempo de Execução":188,"Velocidade":1.0062500000000014}},"1097":{"CHI0G12":{"Aceleração":0.0007812499999997335,"Acima da Velocidade":false,"Batido":false,"Posicao":[565.0,705.8999999999996],"Posição Prevista":2043.8999999998741,"Risco Colisão":[],"Tempo de Execução":188,"Velocidade":1.0187499999999972}},"1113":{"CHI0G12":{"Aceleração":0.0007812500000001776,"Acima da Velocidade":false,"Batido":false,"Posicao":[565.0,722.3999999999996],"Posição Prevista":2072.4000000000815,"Risco Colisão":[],"Tempo de Execução":188,"Velocidade":1.03125}},"1129":{"CHI0G12":{"Aceleração":0.0007812499999997335,"Acima da Velocidade":false,"Batido":false,"Posicao":[565.0,739.0999999999996],"Posição Prevista":2101.0999999998726,"Risco Colisão":[],"Tempo de Execução":188,"Velocidade":1.0437499999999957}},"113":{"CHI0G12":{"Aceleração":0.0007812499999999556,"Acima da Velocidade":false,"Batido":false,"Posicao":[565.0,77.6],"Posição Prevista":683.5999999999792,"Risco Colisão":[],"Tempo de Execução":179,"Velocidade":0.25624999999999964}},"1146":{"CHI0G12":{"Aceleração":-0.0029195501730102068,"Acima da Velocidade":false,"Batido":false,"Posicao":[565.0,755.9999999999995],"Posição Prevista":251.25000000008868,"Risco Colisão":[],"Tempo de Execução":188,"Velocidade":0.9941176470588222}},"1162":{"CHI0G12":{"Aceleração":0.0046645220588237,"Acima da Velocidade":false,"Batido":false,"Posicao":[565.0,773.0999999999996],"Posição Prevista":3948.511764705962,"Risco Colisão":[],"Tempo de Execução":189,"Velocidade":1.0687500000000014}},"1178":{"CHI0G12":{"Aceleração":0.0007812499999997335,"Acima da Velocidade":false,"Batido":false,"Posicao":[565.0,790.3999999999995],"Posição Prevista":2188.399999999874,"Risco Colisão":[],"Tempo de Execução":189,"Velocidade":1.0812499999999972}},"1194":{"CHI0G12":{"Aceleração":0.0007812500000001776,"Acima da Velocidade":false,"Batido":false,"Posicao":[565.0,807.8999999999995],"Posição Prevista":2217.9000000000815,"Risco Colisão":[],"Tempo de Execução":189,"Velocidade":1.09375}},"1210":{"CHI0G12":{"Aceleração":0.0007812499999997335,"Acima da Velocidade":false,"Batido":false,"Posicao":[565.0,825.5999999999995],"Posição Prevista":2247.5999999998726,"Risco Colisão":[],"Tempo de Execução":189,"Velocidade":1.1062499999999957}},"1226":{"CHI0G12":{"Aceleração":0.0007812500000001776,"Acima da Velocidade":false,"Batido":false,"Posicao":[565.0,843.4999999999994],"Posição Prevista":2277.50000000008,"Risco Colisão":[],"Tempo de Execução":189,"Velocidade":1.1187499999999986}},"1242":{"CHI0G12":{"Aceleração":0.0007812500000001776,"Acima da Velocidade":false,"Batido":false,"Posicao":[565.0,861.5999999999995],"Posição Prevista":2307.6000000000827,"Risco Colisão":[],"Tempo de Execução":189,"Velocidade":1.1312500000000014}},"1258":{"CHI0G12":{"Aceleração":0.0007812499999997335,"Acima da Velocidade":false,"Batido":false,"Posicao":[565.0,879.8999999999994],"Posição Prevista":2337.899999999874,"Risco Colisão":[],"Tempo de Execução":189,"Velocidade":1.1437499999999972}},"1274":{"CHI0G12":{"Aceleração":0.0007812500000001776,"Acima da Velocidade":false,"Batido":false,"Posicao":[565.0,898.3999999999994],"Posição Prevista":2368.4000000000815,"Risco Colisão":[],"Tempo de Execução":189,"Velocidade":1.15625}},"129":{"CHI0G12":{"Aceleração":0.0007812500000000666,"Acima da Velocidade":false,"Batido":false,"Posicao":[565.0,81.9],"Posição Prevista":699.9000000000314,"Risco Colisão":[],"Tempo de Execução":180,"Velocidade":0.2687500000000007}},"1290":{"CHI0G12":{"Aceleração":0.0007812499999997335,"Acima da Velocidade":false,"Batido":false,"Posicao":[565.0,917.0999999999993],"Posição Prevista":2399.0999999998726,"Risco Colisão":[],"Tempo de Execução":189,"Velocidade":1.1687499999999957}},"1306":{"CHI0G12":{"Aceleração":0.0007812500000001776,"Acima da Velocidade":false,"Batido":false,"Posicao":[565.0,935.9999999999993],"Posição Prevista":2430.00000000008,"Risco Colisão":[],"Tempo de Execução":189,"Velocidade":1.1812499999999986}},"1322":{"CHI0G12":{"Aceleração":0.0007812499999997335,"Acima da Velocidade":false,"Batido":false,"Posicao":[565.0,955.0999999999992],"Posição Prevista":2461.099999999871,"Risco Colisão":[],"Tempo de Execução":190,"Velocidade":1.1937499999999943}},"1338":null,"1355":null,"1371":null,"1387":null,"1403":null,"1419":null,"1435":null,"145":{"CHI0G12":{"Aceleração":0.0007812499999999556,"Acima da Velocidade":false,"Batido":false,"Posicao":[565.0,86.4],"Posição Prevista":716.3999999999795,"Risco Colisão":[],"Tempo de Execução":180,"Velocidade":0.28125}},"1451":null,"1467":null,"1483":null,"1499":null,"1515":null,"1531":null,"1548":null,"1564":null,"1580":null,"1596":null,"16":{"CHI0G12":{"Batido":false,"Posicao":[565.0,56],"Posição Prevista":56.0,"Risco Colisão":[],"Tempo de Execução":179}},"161":{"CHI0G12":{"Aceleração":0.0007812500000000111,"Acima da Velocidade":false,"Batido":false,"Posicao":[565.0,91.10000000000001],"Posição Prevista":733.1000000000054,"Risco Colisão":[],"Tempo de Execução":180,"Velocidade":0.2937500000000002}},"1612":null,"1628":null,"1644":null,"1660":null,"1676":null,"1692":null,"1708":null,"1724":null,"1740":null,"1757":null,"177":{"CHI0G12":{"Aceleração":0.0007812499999999556,"Acima da Velocidade":false,"Batido":false,"Posicao":[565.0,96.0],"Posição Prevista":749.9999999999791,"Risco Colisão":[],"Tempo de Execução":180,"Velocidade":0.30624999999999947}},"1774":null,"1790":null,"1806":null,"1822":null,"1838":null,"1855":null,"1871":null,"1887":null,"1903":null,"1919":null,"193":{"CHI0G12":{"Aceleração":0.0007812500000000666,"Acima da Velocidade":false,"Batido":false,"Posicao":[565.0,101.10000000000001],"Posição Prevista":767.1000000000313,"Risco Colisão":[],"Tempo de Execução":180,"Velocidade":0.31875000000000053}},"1935":null,"1951":null,"1967":null,"1983":null,"2000":null,"2015":null,"2031":null,"2047":null,"2063":null,"2080":null,"209":{"CHI0G12":{"Aceleração":0.0007812499999999556,"Acima da Velocidade":false,"Batido":false,"Posicao":[565.0,106.4],"Posição Prevista":784.3999999999794,"Risco Colisão":[],"Tempo de Execução":180,"Velocidade":0.3312499999999998}},"2096":null,"2112":null,"2128":null,"2144":null,"2160":null,"2177":null,"2193":null,"2209":null,"2225":null,"2241":null,"225":{"CHI0G12":{"Aceleração":0.0007812500000000111,"Acima da Velocidade":false,"Batido":false,"Posicao":[565.0,111.9],"Posição Prevista":801.9000000000051,"Risco Colisão":[],"Tempo de Execução":180,"Velocidade":0.34375}},"2257":null,"2274":null,"2290":null,"2306":null,"2322":null,"2338":null,"2354":null,"2370":null,"2387":null,"2403":null,"241":{"CHI0G12":{"Aceleração":0.0007812500000000111,"Acima da Velocidade":false,"Batido":false,"Posicao":[565.0,117.60000000000001],"Posição Prevista":819.6000000000054,"Risco Colisão":[],"Tempo de Execução":180,"Velocidade":0.3562500000000002}},"2419":null,"2435":null,"2451":null,"2468":null,"2484":null,"2500":null,"2516":null,"2532":null,"2548":null,"2565":null,"257":{"CHI0G12":{"Aceleração":0.0007812500000000111,"Acima da Velocidade":false,"Batido":false,"Posicao":[565.0,123.50000000000001],"Posição Prevista":837.5000000000055,"Risco Colisão":[],"Tempo de Execução":180,"Velocidade":0.36875000000000036}},"2581":null,"2597":null,"2613":null,"2629":null,"2645":null,"2661":null,"2678":{"URU6M78":null},"2694":{"URU6M78":{"Batido":false,"Posicao":[475.0,61],"Posição Prevista":61.0,"Risco Colisão":[],"Tempo de Execução":242}},"2710":{"URU6M78":{"Acima da Velocidade":false,"Batido":false,"Posicao":[475.0,72],"Posição Prevista":732.0,"Risco Colisão":[],"Tempo de Execução":242,"Velocidade":0.6875}},"2726":{"URU6M78":{"Aceleração":0.0003906249999999778,"Acima da Velocidade":false,"Batido":false,"Posicao":[475.0,83.1],"Posição Prevista":929.0999999999894,"Risco Colisão":[],"Tempo de Execução":242,"Velocidade":0.6937499999999996}},"273":{"CHI0G12":{"Aceleração":0.0007812500000000111,"Acima da Velocidade":false,"Batido":false,"Posicao":[565.0,129.60000000000002],"Posição Prevista":855.6000000000056,"Risco Colisão":[],"Tempo de Execução":180,"Velocidade":0.38125000000000053}},"2742":{"URU6M78":{"Aceleração":0.0007812500000000666,"Acima da Velocidade":false,"Batido":false,"Posicao":[475.0,94.4],"Posição Prevista":1132.4000000000315,"Risco Colisão":[],"Tempo de Execução":242,"Velocidade":0.7062500000000007}},"2758":{"URU6M78":{"Aceleração":0.0007812499999999556,"Acima da Velocidade":false,"Batido":false,"Posicao":[475.0,105.9],"Posição Prevista":1155.8999999999796,"Risco Colisão":[],"Tempo de Execução":243,"Velocidade":0.71875}},"2776":{"URU6M78":{"Aceleração":-0.0038194444444444803,"Acima da Velocidade":false,"Batido":false,"Posicao":[475.0,117.6],"Posição Prevista":-1407.9000000000215,"Risco Colisão":[],"Tempo de Execução":243,"Velocidade":0.6499999999999994}},"2792":{"URU6M78":{"Aceleração":0.0058593750000000625,"Acima da Velocidade":false,"Batido":false,"Posicao":[475.0,129.5],"Posição Prevista":3543.500000000029,"Risco Colisão":[],"Tempo de Execução":243,"Velocidade":0.7437500000000004}},"2808":{"URU6M78":{"Aceleração":0.0007812499999999556,"Acima da Velocidade":false,"Batido":false,"Posicao":[475.0,141.6],"Posição Prevista":1227.5999999999792,"Risco Colisão":[],"Tempo de Execução":243,"Velocidade":0.7562499999999996}},"2824":{"URU6M78":{"Aceleração":0.0007812499999999556,"Acima da Velocidade":false,"Batido":false,"Posicao":[475.0,153.89999999999998],"Posição Prevista":1251.8999999999785,"Risco Colisão":[],"Tempo de Execução":243,"Velocidade":0.7687499999999989}},"2840":{"URU6M78":{"Aceleração":0.0007812500000000666,"Acima da Velocidade":false,"Batido":false,"Posicao":[475.0,166.39999999999998],"Posição Prevista":1276.4000000000306,"Risco Colisão":[],"Tempo de Execução":243,"Velocidade":0.78125}},"2856":{"URU6M78":{"Aceleração":0.0007812499999999556,"Acima da Velocidade":false,"Batido":false,"Posicao":[475.0,179.09999999999997],"Posição Prevista":1301.0999999999788,"Risco Colisão":[],"Tempo de Execução":243,"Velocidade":0.7937499999999993}},"2873":{"URU6M78":{"Aceleração":-0.002054498269896232,"Acima da Velocidade":false,"Batido":false,"Posicao":[475.0,191.99999999999994],"Posição Prevista":-102.75000000002137,"Risco Colisão":[],"Tempo de Execução":244,"Velocidade":0.7588235294117633}},"2889":{"URU6M78":{"Aceleração":0.00374540441176488,"Acima da Velocidade":false,"Batido":false,"Posicao":[475.0,205.09999999999997],"Posição Prevista":2716.982352941258,"Risco Colisão":[],"Tempo de Execução":244,"Velocidade":0.8187500000000014}},"289":{"CHI0G12":{"Aceleração":0.0007812500000000111,"Acima da Velocidade":false,"Batido":false,"Posicao":[565.0,135.90000000000003],"Posição Prevista":873.9000000000059,"Risco Colisão":[],"Tempo de Execução":181,"Velocidade":0.3937500000000007}},"2905":{"URU6M78":{"Aceleração":0.0007812499999998446,"Acima da Velocidade":false,"Batido":false,"Posicao":[475.0,218.39999999999995],"Posição Prevista":1376.3999999999273,"Risco Colisão":[],"Tempo de Execução":244,"Velocidade":0.8312499999999989}},"2921":{"URU6M78":{"Aceleração":0.0007812500000000666,"Acima da Velocidade":false,"Batido":false,"Posicao":[475.0,231.89999999999995],"Posição Prevista":1401.9000000000306,"Risco Colisão":[],"Tempo de Execução":244,"Velocidade":0.84375}},"2938":{"URU6M78":{"Aceleração":-0.0022275086505190687,"Acima da Velocidade":false,"Batido":false,"Posicao":[475.0,245.59999999999994],"Posição Prevista":-91.15000000002033,"Risco Colisão":[],"Tempo de Execução":245,"Velocidade":0.8058823529411758}},"2954":{"URU6M78":{"Aceleração":0.003929227941176311,"Acima da Velocidade":false,"Batido":false,"Posicao":[475.0,259.4999999999999],"Posição Prevista":2904.0882352940407,"Risco Colisão":[],"Tempo de Execução":245,"Velocidade":0.8687499999999968}},"2970":{"URU6M78":{"Aceleração":0.0007812500000002887,"Acima da Velocidade":false,"Batido":false,"Posicao":[475.0,273.5999999999999],"Posição Prevista":1479.6000000001343,"Risco Colisão":[],"Tempo de Execução":245,"Velocidade":0.8812500000000014}},"2986":{"URU6M78":{"Aceleração":0.0007812499999997335,"Acima da Velocidade":false,"Batido":false,"Posicao":[475.0,287.89999999999986],"Posição Prevista":1505.8999999998744,"Risco Colisão":[],"Tempo de Execução":245,"Velocidade":0.8937499999999972}},"3001":{"URU6M78":{"Aceleração":0.004861111111111301,"Acima da Velocidade":false,"Batido":false,"Posicao":[475.0,302.39999999999986],"Posição Prevista":3141.150000000077,"Risco Colisão":[],"Tempo de Execução":245,"Velocidade":0.9666666666666667}},"3018":{"URU6M78":{"Aceleração":-0.005997693194924871,"Acima da Velocidade":false,"Batido":false,"Posicao":[475.0,317.0999999999999],"Posição Prevista":-1920.899999999915,"Risco Colisão":[],"Tempo de Execução":245,"Velocidade":0.8647058823529439}},"3034":{"URU6M78":{"Aceleração":0.004159007352940919,"Acima da Velocidade":false,"Batido":false,"Posicao":[475.0,331.9999999999999],"Posição Prevista":3142.470588235174,"Risco Colisão":[],"Tempo de Execução":245,"Velocidade":0.9312499999999986}},"305":{"CHI0G12":{"Aceleração":0.0007812499999999556,"Acima da Velocidade":false,"Batido":false,"Posicao":[565.0,142.40000000000003],"Posição Prevista":892.3999999999796,"Risco Colisão":[],"Tempo de Execução":181,"Velocidade":0.40625}},"3050":{"URU6M78":{"Aceleração":0.0007812499999999556,"Acima da Velocidade":false,"Batido":false,"Posicao":[475.0,347.09999999999985],"Posição Prevista":1613.0999999999774,"Risco Colisão":[],"Tempo de Execução":246,"Velocidade":0.9437499999999979}},"3066":{"URU6M78":{"Aceleração":0.0007812500000001776,"Acima da Velocidade":false,"Batido":false,"Posicao":[475.0,362.39999999999986],"Posição Prevista":1640.4000000000824,"Risco Colisão":[],"Tempo de Execução":246,"Velocidade":0.9562500000000007}},"3082":{"URU6M78":{"Aceleração":0.0007812499999999556,"Acima da Velocidade":false,"Batido":false,"Posicao":[475.0,377.89999999999986],"Posição Prevista":1667.8999999999794,"Risco Colisão":[],"Tempo de Execução":246,"Velocidade":0.96875}},"3099":{"URU6M78":{"Aceleração":-0.002660034602076161,"Acima da Velocidade":false,"Batido":false,"Posicao":[475.0,393.59999999999985],"Posição Prevista":-48.150000000019645,"Risco Colisão":[],"Tempo de Execução":246,"Velocidade":0.9235294117647053}},"3115":{"URU6M78":{"Aceleração":0.004388786764705832,"Acima da Velocidade":false,"Batido":false,"Posicao":[475.0,409.49999999999983],"Posição Prevista":3385.8529411764457,"Risco Colisão":[],"Tempo de Execução":246,"Velocidade":0.9937499999999986}},"3131":{"URU6M78":{"Aceleração":0.0007812499999999556,"Acima da Velocidade":false,"Batido":false,"Posicao":[475.0,425.5999999999998],"Posição Prevista":1751.5999999999772,"Risco Colisão":[],"Tempo de Execução":246,"Velocidade":1.0062499999999979}},"3147":{"URU6M78":{"Aceleração":0.0007812499999999556,"Acima da Velocidade":false,"Batido":false,"Posicao":[475.0,441.89999999999975],"Posição Prevista":1779.8999999999764,"Risco Colisão":[],"Tempo de Execução":246,"Velocidade":1.0187499999999972}},"3164":{"URU6M78":{"Aceleração":-0.002833044982698795,"Acima da Velocidade":false,"Batido":false,"Posicao":[475.0,458.39999999999975],"Posição Prevista":-25.349999999913507,"Risco Colisão":[],"Tempo de Execução":247,"Velocidade":0.9705882352941176}},"3180":{"URU6M78":{"Aceleração":0.004572610294117603,"Acima da Velocidade":false,"Batido":false,"Posicao":[475.0,475.09999999999974],"Posição Prevista":3584.1588235293907,"Risco Colisão":[],"Tempo de Execução":247,"Velocidade":1.0437499999999993}},"3196":{"URU6M78":{"Aceleração":0.0007812499999999556,"Acima da Velocidade":false,"Batido":false,"Posicao":[475.0,491.9999999999997],"Posição Prevista":1865.999999999978,"Risco Colisão":[],"Tempo de Execução":247,"Velocidade":1.0562499999999986}},"32":{"CHI0G12":{"Acima da Velocidade":false,"Batido":false,"Posicao":[565.0,59.1],"Posição Prevista":245.10000000000008,"Risco Colisão":[],"Tempo de Execução":179,"Velocidade":0.1937500000000001}},"3212":{"URU6M78":{"Aceleração":0.0007812499999999556,"Acima da Velocidade":false,"Batido":false,"Posicao":[475.0,509.0999999999997],"Posição Prevista":1895.0999999999772,"Risco Colisão":[],"Tempo de Execução":247,"Velocidade":1.0687499999999979}},"322":{"CHI0G12":{"Aceleração":-0.000713667820069244,"Acima da Velocidade":false,"Batido":false,"Posicao":[565.0,149.10000000000002],"Posição Prevista":179.8499999999786,"Risco Colisão":[],"Tempo de Execução":181,"Velocidade":0.39411764705882285}},"3229":{"URU6M78":{"Aceleração":-0.0030060553633218345,"Acima da Velocidade":false,"Batido":false,"Posicao":[475.0,526.3999999999996],"Posição Prevista":0.6499999999784905,"Risco Colisão":[],"Tempo de Execução":247,"Velocidade":1.0176470588235267}},"3245":{"URU2Y34":null,"URU6M78":{"Aceleração":0.004756433823529582,"Acima da Velocidade":false,"Batido":false,"Posicao":[475.0,543.8999999999996],"Posição Prevista":3785.664705882431,"Risco Colisão":[],"Tempo de Execução":247,"Velocidade":1.09375}},"3261":{"URU2Y34":{"Batido":false,"Posicao":[745.0,860],"Posição Prevista":860.0,"Risco Colisão":[],"Tempo de Execução":298},"URU6M78":{"Aceleração":0.0007812500000001776,"Acima da Velocidade":false,"Batido":false,"Posicao":[475.0,561.5999999999997],"Posição Prevista":1983.6000000000843,"Risco Colisão":[],"Tempo de Execução":298,"Velocidade":1.1062500000000028}},"3277":{"URU2Y34":{"Acima da Velocidade":false,"Batido":false,"Posicao":[745.0,850],"Posição Prevista":1450.0,"Risco Colisão":[],"Tempo de Execução":298,"Velocidade":0.625},"URU6M78":{"Aceleração":0.0007812499999992895,"Acima da Velocidade":false,"Batido":false,"Posicao":[475.0,579.4999999999995],"Posição Prevista":2013.499999999664,"Risco Colisão":[],"Tempo de Execução":298,"Velocidade":1.1187499999999915}},"3293":{"URU2Y34":{"Aceleração":-0.00019531249999982236,"Acima da Velocidade":false,"Batido":false,"Posicao":[745.0,840.05],"Posição Prevista":1347.0500000000845,"Risco Colisão":[],"Tempo de Execução":298,"Velocidade":0.6218750000000028},"URU6M78":{"Aceleração":0.0007812500000006217,"Acima da Velocidade":false,"Batido":false,"Posicao":[475.0,597.5999999999996],"Posição Prevista":2043.6000000002873,"Risco Colisão":[],"Tempo de Execução":298,"Velocidade":1.1312500000000014}},"3309":{"URU2Y34":{"Aceleração":-0.00019531250000026645,"Acima da Velocidade":false,"Batido":false,"Posicao":[745.0,830.15],"Posição Prevista":1334.149999999876,"Risco Colisão":[],"Tempo de Execução":298,"Velocidade":0.6187499999999986},"URU6M78":{"Aceleração":0.0007812499999997335,"Acima da Velocidade":false,"Batido":false,"Posicao":[475.0,615.8999999999995],"Posição Prevista":2073.899999999874,"Risco Colisão":[],"Tempo de Execução":298,"Velocidade":1.1437499999999972}},"3325":{"URU2Y34":{"Aceleração":-0.00019531249999982236,"Acima da Velocidade":false,"Batido":false,"Posicao":[745.0,820.3],"Posição Prevista":1321.3000000000832,"Risco Colisão":[],"Tempo de Execução":298,"Velocidade":0.6156250000000014},"URU6M78":{"Aceleração":0.0007812500000001776,"Acima da Velocidade":false,"Batido":false,"Posicao":[475.0,634.3999999999995],"Posição Prevista":2104.4000000000815,"Risco Colisão":[],"Tempo de Execução":298,"Velocidade":1.15625}},"3341":{"URU2Y34":{"Aceleração":-0.00019531250000026645,"Acima da Velocidade":false,"Batido":false,"Posicao":[745.0,810.5],"Posição Prevista":1308.4999999998745,"Risco Colisão":[],"Tempo de Execução":299,"Velocidade":0.6124999999999972},"URU6M78":{"Aceleração":0.0007812499999997335,"Acima da Velocidade":false,"Batido":false,"Posicao":[475.0,653.0999999999995],"Posição Prevista":2135.0999999998726,"Risco Colisão":[],"Tempo de Execução":299,"Velocidade":1.1687499999999957}},"3357":{"URU2Y34":{"Aceleração":-0.00019531249999982236,"Acima da Velocidade":false,"Batido":false,"Posicao":[745.0,800.75],"Posição Prevista":1295.7500000000819,"Risco Colisão":[],"Tempo de Execução":299,"Velocidade":0.609375},"URU4O56":null,"URU6M78":{"Aceleração":0.0007812500000001776,"Acima da Velocidade":false,"Batido":false,"Posicao":[475.0,671.9999999999994],"Posição Prevista":2166.00000000008,"Risco Colisão":[],"Tempo de Execução":299,"Velocidade":1.1812499999999986}},"3373":{"URU2Y34":{"Aceleração":-0.00019531249999982236,"Acima da Velocidade":false,"Batido":false,"Posicao":[745.0,791.05],"Posição Prevista":1283.0500000000845,"Risco Colisão":[],"Tempo de Execução":349,"Velocidade":0.6062500000000028},"URU4O56":{"Batido":false,"Posicao":[385.0,53],"Posição Prevista":53.0,"Risco Colisão":[],"Tempo de Execução":349},"URU6M78":{"Aceleração":0.0007812500000001776,"Acima da Velocidade":false,"Batido":false,"Posicao":[475.0,691.0999999999995],"Posição Prevista":2197.1000000000827,"Risco Colisão":[],"Tempo de Execução":349,"Velocidade":1.1937500000000014}},"338":{"CHI0G12":{"Aceleração":0.002320772058823594,"Acima da Velocidade":false,"Batido":false,"Posicao":[565.0,156.00000000000003],"Posição Prevista":1639.4117647059124,"Risco Colisão":[],"Tempo de Execução":181,"Velocidade":0.43125000000000036}},"3389":{"URU2Y34":{"Aceleração":-0.00019531250000026645,"Acima da Velocidade":false,"Batido":false,"Posicao":[745.0,781.4],"Posição Prevista":1270.399999999876,"Risco Colisão":[],"Tempo de Execução":349,"Velocidade":0.6031249999999986},"URU4O56":{"Acima da Velocidade":false,"Batido":false,"Posicao":[385.0,56],"Posição Prevista":236.0,"Risco Colisão":[],"Tempo de Execução":349,"Velocidade":0.1875},"URU6M78":{"Aceleração":0.0007812499999997335,"Acima da Velocidade":false,"Batido":false,"Posicao":[475.0,710.3999999999994],"Posição Prevista":2228.399999999874,"Risco Colisão":[],"Tempo de Execução":349,"Velocidade":1.2062499999999972}},"3405":{"URU2Y34":{"Aceleração":-0.00019531249999982236,"Acima da Velocidade":false,"Batido":false,"Posicao":[745.0,771.8],"Posição Prevista":1257.8000000000832,"Risco Colisão":[],"Tempo de Execução":349,"Velocidade":0.6000000000000014},"URU4O56":{"Aceleração":0.00039062500000000555,"Acima da Velocidade":false,"Batido":false,"Posicao":[385.0,59.1],"Posição Prevista":425.10000000000264,"Risco Colisão":[],"Tempo de Execução":349,"Velocidade":0.1937500000000001},"URU6M78":{"Aceleração":0.0007812500000001776,"Acima da Velocidade":false,"Batido":false,"Posicao":[475.0,729.8999999999994],"Posição Prevista":2259.9000000000815,"Risco Colisão":[],"Tempo de Execução":349,"Velocidade":1.21875}},"3421":{"URU2Y34":{"Aceleração":-0.00019531250000026645,"Acima da Velocidade":false,"Batido":false,"Posicao":[745.0,762.25],"Posição Prevista":1245.2499999998745,"Risco Colisão":[],"Tempo de Execução":350,"Velocidade":0.5968749999999972},"URU4O56":{"Aceleração":0.0007812499999999833,"Acima da Velocidade":false,"Batido":false,"Posicao":[385.0,62.4],"Posição Prevista":620.3999999999921,"Risco Colisão":[],"Tempo de Execução":350,"Velocidade":0.20624999999999982},"URU6M78":{"Aceleração":0.0007812499999997335,"Acima da Velocidade":false,"Batido":false,"Posicao":[475.0,749.5999999999993],"Posição Prevista":2291.5999999998726,"Risco Colisão":[],"Tempo de Execução":350,"Velocidade":1.2312499999999957}},"3437":{"URU2Y34":{"Aceleração":-0.00019531249999982236,"Acima da Velocidade":false,"Batido":false,"Posicao":[745.0,752.75],"Posição Prevista":1232.7500000000819,"Risco Colisão":[],"Tempo de Execução":350,"Velocidade":0.59375},"URU4O56":{"Aceleração":0.0007812500000000389,"Acima da Velocidade":false,"Batido":false,"Posicao":[385.0,65.9],"Posição Prevista":635.9000000000183,"Risco Colisão":[],"Tempo de Execução":350,"Velocidade":0.21875000000000044},"URU6M78":{"Aceleração":0.0007812500000001776,"Acima da Velocidade":false,"Batido":false,"Posicao":[475.0,769.4999999999993],"Posição Prevista":2323.50000000008,"Risco Colisão":[],"Tempo de Execução":350,"Velocidade":1.2437499999999986}},"3453":{"URU2Y34":{"Aceleração":-0.00019531249999982236,"Acima da Velocidade":false,"Batido":false,"Posicao":[745.0,743.3],"Posição Prevista":1220.3000000000845,"Risco Colisão":[],"Tempo de Execução":350,"Velocidade":0.5906250000000028},"URU4O56":{"Aceleração":0.0007812499999999278,"Acima da Velocidade":false,"Batido":false,"Posicao":[385.0,69.6],"Posição Prevista":651.599999999966,"Risco Colisão":[],"Tempo de Execução":350,"Velocidade":0.2312499999999993},"URU6M78":{"Aceleração":0.0007812500000001776,"Acima da Velocidade":false,"Batido":false,"Posicao":[475.0,789.5999999999993],"Posição Prevista":2355.6000000000827,"Risco Colisão":[],"Tempo de Execução":350,"Velocidade":1.2562500000000014}},"3469":{"URU2Y34":{"Aceleração":-0.00019531250000026645,"Acima da Velocidade":false,"Batido":false,"Posicao":[745.0,733.9],"Posição Prevista":1207.899999999876,"Risco Colisão":[],"Tempo de Execução":351,"Velocidade":0.5874999999999986},"URU4O56":{"Aceleração":0.0007812500000000666,"Acima da Velocidade":false,"Batido":false,"Posicao":[385.0,73.5],"Posição Prevista":667.500000000031,"Risco Colisão":[],"Tempo de Execução":351,"Velocidade":0.24375000000000036},"URU6M78":{"Aceleração":0.0007812499999997335,"Acima da Velocidade":false,"Batido":false,"Posicao":[475.0,809.8999999999993],"Posição Prevista":2387.8999999998737,"Risco Colisão":[],"Tempo de Execução":351,"Velocidade":1.2687499999999972}},"3485":{"URU2Y34":{"Aceleração":-0.00019531249999982236,"Acima da Velocidade":false,"Batido":false,"Posicao":[745.0,724.55],"Posição Prevista":1195.5500000000832,"Risco Colisão":[],"Tempo de Execução":351,"Velocidade":0.5843750000000014},"URU4O56":{"Aceleração":0.0007812499999999556,"Acima da Velocidade":false,"Batido":false,"Posicao":[385.0,77.6],"Posição Prevista":683.5999999999792,"Risco Colisão":[],"Tempo de Execução":351,"Velocidade":0.25624999999999964},"URU6M78":{"Aceleração":0.0007812500000001776,"Acima da Velocidade":false,"Batido":false,"Posicao":[475.0,830.3999999999993],"Posição Prevista":2420.400000000081,"Risco Colisão":[],"Tempo de Execução":351,"Velocidade":1.28125}},"3501":{"URU2Y34":{"Aceleração":-0.00019531250000026645,"Acima da Velocidade":false,"Batido":false,"Posicao":[745.0,715.25],"Posição Prevista":1183.2499999998745,"Risco Colisão":[],"Tempo de Execução":351,"Velocidade":0.5812499999999972},"URU4O56":{"Aceleração":0.0007812500000000666,"Acima da Velocidade":false,"Batido":false,"Posicao":[385.0,81.9],"Posição Prevista":699.9000000000314,"Risco Colisão":[],"Tempo de Execução":351,"Velocidade":0.2687500000000007},"URU6M78":{"Aceleração":0.0007812499999997335,"Acima da Velocidade":false,"Batido":false,"Posicao":[475.0,851.0999999999992],"Posição Prevista":2453.099999999872,"Risco Colisão":[],"Tempo de Execução":351,"Velocidade":1.2937499999999957}},"3517":{"URU2Y34":{"Aceleração":-0.00019531249999982236,"Acima da Velocidade":false,"Batido":false,"Posicao":[745.0,706.0],"Posição Prevista":1171.0000000000819,"Risco Colisão":[],"Tempo de Execução":351,"Velocidade":0.578125},"URU4O56":{"Aceleração":0.0007812499999999556,"Acima da Velocidade":false,"Batido":false,"Posicao":[385.0,86.4],"Posição Prevista":716.3999999999795,"Risco Colisão":[],"Tempo de Execução":351,"Velocidade":0.28125},"URU6M78":{"Aceleração":0.0007812500000001776,"Acima da Velocidade":false,"Batido":false,"Posicao":[475.0,871.9999999999992],"Posição Prevista":2486.0000000000796,"Risco Colisão":[],"Tempo de Execução":352,"Velocidade":1.3062499999999986}},"3533":{"URU2Y34":{"Aceleração":-0.00019531249999982236,"Acima da Velocidade":false,"Batido":false,"Posicao":[745.0,696.8],"Posição Prevista":1158.8000000000845,"Risco Colisão":[],"Tempo de Execução":352,"Velocidade":0.5750000000000028},"URU4O56":{"Aceleração":0.0007812500000000111,"Acima da Velocidade":false,"Batido":false,"Posicao":[385.0,91.10000000000001],"Posição Prevista":733.1000000000054,"Risco Colisão":[],"Tempo de Execução":352,"Velocidade":0.2937500000000002},"URU6M78":{"Aceleração":0.0007812500000001776,"Acima da Velocidade":false,"Batido":false,"Posicao":[475.0,893.0999999999992],"Posição Prevista":2519.100000000082,"Risco Colisão":[],"Tempo de Execução":352,"Velocidade":1.3187500000000014}},"354":{"CHI0G12":{"Aceleração":0.0007812499999999556,"Acima da Velocidade":false,"Batido":false,"Posicao":[565.0,163.10000000000002],"Posição Prevista":949.0999999999792,"Risco Colisão":[],"Tempo de Execução":181,"Velocidade":0.44374999999999964}},"3549":{"URU2Y34":{"Aceleração":-0.00019531250000026645,"Acima da Velocidade":false,"Batido":false,"Posicao":[745.0,687.65],"Posição Prevista":1146.649999999876,"Risco Colisão":[],"Tempo de Execução":352,"Velocidade":0.5718749999999986},"URU4O56":{"Aceleração":0.0007812499999999556,"Acima da Velocidade":false,"Batido":false,"Posicao":[385.0,96.0],"Posição Prevista":749.9999999999791,"Risco Colisão":[],"Tempo de Execução":352,"Velocidade":0.30624999999999947},"URU6M78":{"Aceleração":0.0007812499999997335,"Acima da Velocidade":false,"Batido":false,"Posicao":[475.0,914.3999999999992],"Posição Prevista":2552.3999999998737,"Risco Colisão":[],"Tempo de Execução":352,"Velocidade":1.3312499999999972}},"3565":{"URU2Y34":{"Aceleração":-0.00019531249999982236,"Acima da Velocidade":false,"Batido":false,"Posicao":[745.0,678.55],"Posição Prevista":1134.5500000000832,"Risco Colisão":[],"Tempo de Execução":352,"Velocidade":0.5687500000000014},"URU4O56":{"Aceleração":0.0007812500000000666,"Acima da Velocidade":false,"Batido":false,"Posicao":[385.0,101.10000000000001],"Posição Prevista":767.1000000000313,"Risco Colisão":[],"Tempo de Execução":352,"Velocidade":0.31875000000000053},"URU6M78":{"Aceleração":0.0007812500000001776,"Acima da Velocidade":false,"Batido":false,"Posicao":[475.0,935.8999999999992],"Posição Prevista":2585.900000000081,"Risco Colisão":[],"Tempo de Execução":352,"Velocidade":1.34375}},"3582":{"URU2Y34":null,"URU4O56":{"Aceleração":-0.00041089965397927974,"Acima da Velocidade":false,"Batido":false,"Posicao":[385.0,106.4],"Posição Prevista":210.64999999997855,"Risco Colisão":[],"Tempo de Execução":352,"Velocidade":0.3117647058823528},"URU6M78":{"Aceleração":-0.003957612456747646,"Acima da Velocidade":false,"Batido":false,"Posicao":[475.0,957.5999999999991],"Posição Prevista":200.8499999998694,"Risco Colisão":[],"Tempo de Execução":352,"Velocidade":1.27647058823529}},"3598":{"URU2Y34":{"Batido":false,"Posicao":[745.0,669.5],"Posição Prevista":669.5,"Risco Colisão":[],"Tempo de Execução":352},"URU4O56":{"Aceleração":0.0019990808823529514,"Acima da Velocidade":false,"Batido":false,"Posicao":[385.0,111.9],"Posição Prevista":1363.07647058824,"Risco Colisão":[],"Tempo de Execução":352,"Velocidade":0.34375}},"3614":{"URU2Y34":{"Acima da Velocidade":false,"Batido":false,"Posicao":[745.0,660.5],"Posição Prevista":1200.5,"Risco Colisão":[],"Tempo de Execução":352,"Velocidade":0.5625},"URU4O56":{"Aceleração":0.0007812500000000111,"Acima da Velocidade":false,"Batido":false,"Posicao":[385.0,117.60000000000001],"Posição Prevista":819.6000000000054,"Risco Colisão":[],"Tempo de Execução":352,"Velocidade":0.3562500000000002}},"3630":{"URU2Y34":{"Aceleração":-0.00019531250000026645,"Acima da Velocidade":false,"Batido":false,"Posicao":[745.0,651.5500000000001],"Posição Prevista":1098.5499999998733,"Risco Colisão":[],"Tempo de Execução":352,"Velocidade":0.5593749999999957},"URU4O56":{"Aceleração":0.0007812500000000111,"Acima da Velocidade":false,"Batido":false,"Posicao":[385.0,123.50000000000001],"Posição Prevista":837.5000000000055,"Risco Colisão":[],"Tempo de Execução":353,"Velocidade":0.36875000000000036}},"3646":{"URU2Y34":{"Aceleração":-0.00019531249999982236,"Acima da Velocidade":false,"Batido":false,"Posicao":[745.0,642.6500000000001],"Posição Prevista":1086.6500000000806,"Risco Colisão":[],"Tempo de Execução":353,"Velocidade":0.5562499999999986},"URU4O56":{"Aceleração":0.0007812500000000111,"Acima da Velocidade":false,"Batido":false,"Posicao":[385.0,129.60000000000002],"Posição Prevista":855.6000000000056,"Risco Colisão":[],"Tempo de Execução":353,"Velocidade":0.38125000000000053}},"3662":{"URU2Y34":{"Aceleração":-0.00019531249999982236,"Acima da Velocidade":false,"Batido":false,"Posicao":[745.0,633.8000000000001],"Posição Prevista":1074.8000000000834,"Risco Colisão":[],"Tempo de Execução":353,"Velocidade":0.5531250000000014},"URU4O56":{"Aceleração":0.0007812500000000111,"Acima da Velocidade":false,"Batido":false,"Posicao":[385.0,135.90000000000003],"Posição Prevista":873.9000000000059,"Risco Colisão":[],"Tempo de Execução":353,"Velocidade":0.3937500000000007}},"3678":{"URU2Y34":{"Aceleração":-0.00019531250000026645,"Acima da Velocidade":false,"Batido":false,"Posicao":[745.0,625.0000000000001],"Posição Prevista":1062.9999999998745,"Risco Colisão":[],"Tempo de Execução":353,"Velocidade":0.5499999999999972},"URU4O56":{"Aceleração":0.0007812499999999556,"Acima da Velocidade":false,"Batido":false,"Posicao":[385.0,142.40000000000003],"Posição Prevista":892.3999999999796,"Risco Colisão":[],"Tempo de Execução":353,"Velocidade":0.40625}},"3694":{"URU2Y34":{"Aceleração":-0.00019531249999982236,"Acima da Velocidade":false,"Batido":false,"Posicao":[745.0,616.2500000000001],"Posição Prevista":1051.2500000000819,"Risco Colisão":[],"Tempo de Execução":353,"Velocidade":0.546875},"URU4O56":{"Aceleração":0.0007812499999999556,"Acima da Velocidade":false,"Batido":false,"Posicao":[385.0,149.10000000000002],"Posição Prevista":911.0999999999789,"Risco Colisão":[],"Tempo de Execução":353,"Velocidade":0.4187499999999993}},"370":{"CHI0G12":{"Aceleração":0.0007812500000000666,"Acima da Velocidade":false,"Batido":false,"Posicao":[565.0,170.40000000000003],"Posição Prevista":968.4000000000315,"Risco Colisão":[],"Tempo de Execução":181,"Velocidade":0.4562500000000007}},"3710":{"URU2Y34":{"Aceleração":-0.00019531250000026645,"Acima da Velocidade":false,"Batido":false,"Posicao":[745.0,607.5500000000002],"Posição Prevista":1039.5499999998733,"Risco Colisão":[],"Tempo de Execução":354,"Velocidade":0.5437499999999957},"URU4O56":{"Aceleração":0.0007812500000000666,"Acima da Velocidade":false,"Batido":false,"Posicao":[385.0,156.00000000000003],"Posição Prevista":930.000000000031,"Risco Colisão":[],"Tempo de Execução":354,"Velocidade":0.43125000000000036}},"3727":{"URU2Y34":{"Aceleração":-0.0020544982698956315,"Acima da Velocidade":false,"Batido":false,"Posicao":[745.0,598.9000000000001],"Posição Prevista":49.15000000029795,"Risco Colisão":[],"Tempo de Execução":354,"Velocidade":0.50882352941177},"URU4O56":{"Aceleração":-0.0008001730103806624,"Acima da Velocidade":false,"Batido":false,"Posicao":[385.0,163.10000000000002],"Posição Prevista":172.8499999999791,"Risco Colisão":[],"Tempo de Execução":354,"Velocidade":0.4176470588235291}},"3743":{"URU2Y34":{"Aceleração":0.0017922794117640195,"Acima da Velocidade":false,"Batido":false,"Posicao":[745.0,590.3000000000002],"Posição Prevista":1932.1823529408548,"Risco Colisão":[],"Tempo de Execução":354,"Velocidade":0.5374999999999943},"URU4O56":{"Aceleração":0.002412683823529476,"Acima da Velocidade":false,"Batido":false,"Posicao":[385.0,170.40000000000003],"Posição Prevista":1720.1647058823833,"Risco Colisão":[],"Tempo de Execução":354,"Velocidade":0.4562500000000007}},"3759":{"URU2Y34":{"Aceleração":-0.00019531249999982236,"Acima da Velocidade":false,"Batido":false,"Posicao":[745.0,581.7500000000002],"Posição Prevista":1004.7500000000794,"Risco Colisão":[],"Tempo de Execução":354,"Velocidade":0.5343749999999972},"URU4O56":{"Aceleração":0.0007812499999999556,"Acima da Velocidade":false,"Batido":false,"Posicao":[385.0,177.90000000000003],"Posição Prevista":987.8999999999796,"Risco Colisão":[],"Tempo de Execução":355,"Velocidade":0.46875}},"3776":{"URU2Y34":{"Aceleração":-0.0020220588235292446,"Acima da Velocidade":false,"Batido":false,"Posicao":[745.0,573.2500000000002],"Posição Prevista":31.37500000008731,"Risco Colisão":[],"Tempo de Execução":355,"Velocidade":0.5},"URU4O56":{"Aceleração":-0.00092993079584779,"Acima da Velocidade":false,"Batido":false,"Posicao":[385.0,185.60000000000002],"Posição Prevista":163.84999999997893,"Risco Colisão":[],"Tempo de Execução":355,"Velocidade":0.45294117647058757}},"3792":{"URU2Y34":{"Aceleração":0.0017578125000001776,"Acima da Velocidade":false,"Batido":false,"Posicao":[745.0,564.8000000000002],"Posição Prevista":1881.8000000000848,"Risco Colisão":[],"Tempo de Execução":355,"Velocidade":0.5281250000000028},"URU4O56":{"Aceleração":0.00255055147058841,"Acima da Velocidade":false,"Batido":false,"Posicao":[385.0,193.50000000000006],"Posição Prevista":1842.7941176471413,"Risco Colisão":[],"Tempo de Execução":355,"Velocidade":0.49375000000000213}},"3808":{"URU2Y34":{"Aceleração":-0.00019531250000071054,"Acima da Velocidade":false,"Batido":false,"Posicao":[745.0,556.4000000000003],"Posição Prevista":970.3999999996647,"Risco Colisão":[],"Tempo de Execução":355,"Velocidade":0.5249999999999915},"URU4O56":{"Aceleração":0.0007812499999998446,"Acima da Velocidade":false,"Batido":false,"Posicao":[385.0,201.60000000000005],"Posição Prevista":1047.599999999928,"Risco Colisão":[],"Tempo de Execução":355,"Velocidade":0.5062499999999996}},"3824":{"URU2Y34":{"Aceleração":-0.00019531249999937828,"Acima da Velocidade":false,"Batido":false,"Posicao":[745.0,548.0500000000003],"Posição Prevista":959.050000000288,"Risco Colisão":[],"Tempo de Execução":355,"Velocidade":0.5218750000000014},"URU4O56":{"Aceleração":0.0007812499999999556,"Acima da Velocidade":false,"Batido":false,"Posicao":[385.0,209.90000000000003],"Posição Prevista":1067.8999999999785,"Risco Colisão":[],"Tempo de Execução":356,"Velocidade":0.5187499999999989}},"3840":{"URU2Y34":{"Aceleração":-0.00019531250000026645,"Acima da Velocidade":false,"Batido":false,"Posicao":[745.0,539.7500000000003],"Posição Prevista":947.749999999875,"Risco Colisão":[],"Tempo de Execução":356,"Velocidade":0.5187499999999972},"URU4O56":{"Aceleração":0.0007812500000000666,"Acima da Velocidade":false,"Batido":false,"Posicao":[385.0,218.40000000000003],"Posição Prevista":1088.4000000000308,"Risco Colisão":[],"Tempo de Execução":356,"Velocidade":0.53125}},"3857":{"URU2Y34":{"Aceleração":-0.001967993079584608,"Acima da Velocidade":false,"Batido":false,"Posicao":[745.0,531.5000000000003],"Posição Prevista":2.750000000087425,"Risco Colisão":[],"Tempo de Execução":356,"Velocidade":0.4852941176470588},"URU4O56":{"Aceleração":-0.0011461937716262412,"Acima da Velocidade":false,"Batido":false,"Posicao":[385.0,227.10000000000005],"Posição Prevista":152.85000000003038,"Risco Colisão":[],"Tempo de Execução":356,"Velocidade":0.5117647058823539}},"386":{"CHI0G12":{"Aceleração":0.0007812499999999556,"Acima da Velocidade":false,"Batido":false,"Posicao":[565.0,177.90000000000003],"Posição Prevista":987.8999999999796,"Risco Colisão":[],"Tempo de Execução":181,"Velocidade":0.46875}},"3873":{"URU2Y34":{"Aceleração":0.0017003676470585573,"Acima da Velocidade":false,"Batido":false,"Posicao":[745.0,523.3000000000004],"Posição Prevista":1798.8294117645796,"Risco Colisão":[],"Tempo de Execução":356,"Velocidade":0.5124999999999957},"URU4O56":{"Aceleração":0.0027803308823529035,"Acima da Velocidade":false,"Batido":false,"Posicao":[385.0,236.00000000000006],"Posição Prevista":2051.1764705882183,"Risco Colisão":[],"Tempo de Execução":356,"Velocidade":0.5562500000000004}},"3889":{"URU2Y34":{"Aceleração":-0.00019531249999937828,"Acima da Velocidade":false,"Batido":false,"Posicao":[745.0,515.1500000000003],"Posição Prevista":914.1500000002923,"Risco Colisão":[],"Tempo de Execução":356,"Velocidade":0.5093750000000057},"URU4O56":{"Aceleração":0.0007812499999999556,"Acima da Velocidade":false,"Batido":false,"Posicao":[385.0,245.10000000000005],"Posição Prevista":1151.0999999999792,"Risco Colisão":[],"Tempo de Execução":356,"Velocidade":0.5687499999999996}},"3905":{"URU2Y34":{"Aceleração":-0.00019531250000071054,"Acima da Velocidade":false,"Batido":false,"Posicao":[745.0,507.0500000000004],"Posição Prevista":903.0499999996675,"Risco Colisão":[],"Tempo de Execução":356,"Velocidade":0.5062499999999943},"URU4O56":{"Aceleração":0.0007812500000000666,"Acima da Velocidade":false,"Batido":false,"Posicao":[385.0,254.40000000000006],"Posição Prevista":1172.4000000000315,"Risco Colisão":[],"Tempo de Execução":356,"Velocidade":0.5812500000000007}},"3921":{"URU2Y34":{"Aceleração":-0.00019531249999982236,"Acima da Velocidade":false,"Batido":false,"Posicao":[745.0,499.00000000000045],"Posição Prevista":892.0000000000796,"Risco Colisão":[],"Tempo de Execução":357,"Velocidade":0.5031249999999972},"URU4O56":{"Aceleração":0.0007812500000000666,"Acima da Velocidade":false,"Batido":false,"Posicao":[385.0,263.9000000000001],"Posição Prevista":1193.9000000000324,"Risco Colisão":[],"Tempo de Execução":357,"Velocidade":0.5937500000000018}},"3937":{"URU2Y34":{"Aceleração":-0.00019531249999982236,"Acima da Velocidade":false,"Batido":false,"Posicao":[745.0,491.00000000000045],"Posição Prevista":881.0000000000823,"Risco Colisão":[],"Tempo de Execução":357,"Velocidade":0.5},"URU4O56":{"Aceleração":0.0007812499999996225,"Acima da Velocidade":false,"Batido":false,"Posicao":[385.0,273.6],"Posição Prevista":1215.599999999822,"Risco Colisão":[],"Tempo de Execução":357,"Velocidade":0.6062499999999957}},"3953":{"URU2Y34":{"Aceleração":-0.0001953125000000444,"Acima da Velocidade":false,"Batido":false,"Posicao":[745.0,483.05000000000047],"Posição Prevista":870.0499999999793,"Risco Colisão":[],"Tempo de Execução":357,"Velocidade":0.4968749999999993},"URU4O56":{"Aceleração":0.0007812500000003997,"Acima da Velocidade":false,"Batido":false,"Posicao":[385.0,283.50000000000006],"Posição Prevista":1237.5000000001862,"Risco Colisão":[],"Tempo de Execução":357,"Velocidade":0.6187500000000021}},"3969":{"URU2Y34":{"Aceleração":-0.0001953125000000444,"Acima da Velocidade":false,"Batido":false,"Posicao":[745.0,475.1500000000005],"Posição Prevista":859.1499999999787,"Risco Colisão":[],"Tempo de Execução":357,"Velocidade":0.4937499999999986},"URU4O56":{"Aceleração":0.0007812499999997335,"Acima da Velocidade":false,"Batido":false,"Posicao":[385.0,293.6],"Posição Prevista":1259.5999999998753,"Risco Colisão":[],"Tempo de Execução":357,"Velocidade":0.6312499999999979}},"3985":{"URU2Y34":{"Aceleração":-0.0001953125000000444,"Acima da Velocidade":false,"Batido":false,"Posicao":[745.0,467.3000000000005],"Posição Prevista":848.299999999978,"Risco Colisão":[],"Tempo de Execução":357,"Velocidade":0.49062499999999787},"URU4O56":{"Aceleração":0.0007812500000001776,"Acima da Velocidade":false,"Batido":false,"Posicao":[385.0,303.90000000000003],"Posição Prevista":1281.9000000000826,"Risco Colisão":[],"Tempo de Execução":357,"Velocidade":0.6437500000000007}},"4001":{"URU2Y34":{"Aceleração":-0.0001953125000000444,"Acima da Velocidade":false,"Batido":false,"Posicao":[745.0,459.50000000000057],"Posição Prevista":837.4999999999774,"Risco Colisão":[],"Tempo de Execução":357,"Velocidade":0.48749999999999716},"URU4O56":{"Aceleração":0.0007812499999999556,"Acima da Velocidade":false,"Batido":false,"Posicao":[385.0,314.40000000000003],"Posição Prevista":1304.3999999999796,"Risco Colisão":[],"Tempo de Execução":357,"Velocidade":0.65625}},"4017":{"URU2Y34":{"Aceleração":-0.00019531249999982236,"Acima da Velocidade":false,"Batido":false,"Posicao":[745.0,451.75000000000057],"Posição Prevista":826.7500000000824,"Risco Colisão":[],"Tempo de Execução":358,"Velocidade":0.484375},"URU4O56":{"Aceleração":0.0007812499999999556,"Acima da Velocidade":false,"Batido":false,"Posicao":[385.0,325.1],"Posição Prevista":1327.099999999979,"Risco Colisão":[],"Tempo de Execução":358,"Velocidade":0.6687499999999993}},"402":{"CHI0G12":{"Aceleração":0.0007812499999999556,"Acima da Velocidade":false,"Batido":false,"Posicao":[565.0,185.60000000000002],"Posição Prevista":1007.5999999999789,"Risco Colisão":[],"Tempo de Execução":181,"Velocidade":0.4812499999999993}},"4033":{"URU2Y34":{"Aceleração":-0.0001953125000000444,"Acima da Velocidade":false,"Batido":false,"Posicao":[745.0,444.0500000000006],"Posição Prevista":816.0499999999795,"Risco Colisão":[],"Tempo de Execução":358,"Velocidade":0.4812499999999993},"URU4O56":{"Aceleração":0.0007812499999999556,"Acima da Velocidade":false,"Batido":false,"Posicao":[385.0,336.0],"Posição Prevista":1349.9999999999782,"Risco Colisão":[],"Tempo de Execução":358,"Velocidade":0.6812499999999986}},"4049":{"URU2Y34":{"Aceleração":-0.0001953125000000444,"Acima da Velocidade":false,"Batido":false,"Posicao":[745.0,436.4000000000006],"Posição Prevista":805.3999999999787,"Risco Colisão":[],"Tempo de Execução":358,"Velocidade":0.4781249999999986},"URU4O56":{"Aceleração":0.0007812500000001776,"Acima da Velocidade":false,"Batido":false,"Posicao":[385.0,347.1],"Posição Prevista":1373.1000000000831,"Risco Colisão":[],"Tempo de Execução":358,"Velocidade":0.6937500000000014}},"4065":{"URU2Y34":{"Aceleração":-0.0001953125000000444,"Acima da Velocidade":false,"Batido":false,"Posicao":[745.0,428.80000000000064],"Posição Prevista":794.7999999999781,"Risco Colisão":[],"Tempo de Execução":358,"Velocidade":0.47499999999999787},"URU4O56":{"Aceleração":0.0007812499999999556,"Acima da Velocidade":false,"Batido":false,"Posicao":[385.0,358.40000000000003],"Posição Prevista":1396.3999999999803,"Risco Colisão":[],"Tempo de Execução":358,"Velocidade":0.7062500000000007}},"4082":{"URU2Y34":{"Aceleração":-0.0018166089965398252,"Acima da Velocidade":false,"Batido":false,"Posicao":[745.0,421.2500000000007],"Posição Prevista":-70.7500000000191,"Risco Colisão":[],"Tempo de Execução":359,"Velocidade":0.44411764705882084},"URU4O56":{"Aceleração":-0.0017517301038062678,"Acima da Velocidade":false,"Batido":false,"Posicao":[385.0,369.90000000000003],"Posição Prevista":148.64999999997963,"Risco Colisão":[],"Tempo de Execução":359,"Velocidade":0.6764705882352942}},"4098":{"URU2Y34":{"Aceleração":0.0015395220588236974,"Acima da Velocidade":false,"Batido":false,"Posicao":[745.0,413.7500000000007],"Posição Prevista":1573.1617647059604,"Risco Colisão":[],"Tempo de Execução":359,"Velocidade":0.46875},"URU4O56":{"Aceleração":0.003423713235294071,"Acima da Velocidade":false,"Batido":false,"Posicao":[385.0,381.6],"Posição Prevista":2661.2470588235074,"Risco Colisão":[],"Tempo de Execução":359,"Velocidade":0.7312499999999993}},"4114":{"URU2Y34":{"Aceleração":-0.0001953125000000444,"Acima da Velocidade":false,"Batido":false,"Posicao":[745.0,406.3000000000007],"Posição Prevista":763.2999999999795,"Risco Colisão":[],"Tempo de Execução":359,"Velocidade":0.4656249999999993},"URU4O56":{"Aceleração":0.0007812499999999556,"Acima da Velocidade":false,"Batido":false,"Posicao":[385.0,393.5],"Posição Prevista":1467.4999999999782,"Risco Colisão":[],"Tempo de Execução":359,"Velocidade":0.7437499999999986}},"4130":{"URU2Y34":{"Aceleração":-0.0001953125000000444,"Acima da Velocidade":false,"Batido":false,"Posicao":[745.0,398.9000000000007],"Posição Prevista":752.899999999979,"Risco Colisão":[],"Tempo de Execução":359,"Velocidade":0.4624999999999986},"URU4O56":{"Aceleração":0.0007812499999999556,"Acima da Velocidade":false,"Batido":false,"Posicao":[385.0,405.59999999999997],"Posição Prevista":1491.5999999999774,"Risco Colisão":[],"Tempo de Execução":359,"Velocidade":0.7562499999999979}},"4146":{"URU2Y34":{"Aceleração":-0.0001953125000000444,"Acima da Velocidade":false,"Batido":false,"Posicao":[745.0,391.55000000000075],"Posição Prevista":742.5499999999782,"Risco Colisão":[],"Tempo de Execução":359,"Velocidade":0.45937499999999787},"URU4O56":{"Aceleração":0.0007812500000001776,"Acima da Velocidade":false,"Batido":false,"Posicao":[385.0,417.9],"Posição Prevista":1515.9000000000824,"Risco Colisão":[],"Tempo de Execução":359,"Velocidade":0.7687500000000007}},"4162":{"URU2Y34":{"Aceleração":-0.0001953125000000444,"Acima da Velocidade":false,"Batido":false,"Posicao":[745.0,384.2500000000008],"Posição Prevista":732.2499999999776,"Risco Colisão":[],"Tempo de Execução":360,"Velocidade":0.45624999999999716},"URU4O56":{"Aceleração":0.0007812499999999556,"Acima da Velocidade":false,"Batido":false,"Posicao":[385.0,430.4],"Posição Prevista":1540.3999999999796,"Risco Colisão":[],"Tempo de Execução":360,"Velocidade":0.78125}},"4179":{"URU2Y34":{"Aceleração":-0.0017517301038060622,"Acima da Velocidade":false,"Batido":false,"Posicao":[745.0,377.0000000000008],"Posição Prevista":-99.2499999999128,"Risco Colisão":[],"Tempo de Execução":360,"Velocidade":0.4264705882352941},"URU4O56":{"Aceleração":-0.002011245674740523,"Acima da Velocidade":false,"Batido":false,"Posicao":[385.0,443.09999999999997],"Posição Prevista":158.84999999997922,"Risco Colisão":[],"Tempo de Execução":360,"Velocidade":0.7470588235294111}},"418":{"CHI0G12":{"Aceleração":0.0007812500000001776,"Acima da Velocidade":false,"Batido":false,"Posicao":[565.0,193.50000000000006],"Posição Prevista":1027.500000000084,"Risco Colisão":[],"Tempo de Execução":181,"Velocidade":0.49375000000000213}},"4195":{"URU2Y34":{"Aceleração":0.0014705882352940743,"Acima da Velocidade":false,"Batido":false,"Posicao":[745.0,369.8000000000008],"Posição Prevista":1479.4470588235095,"Risco Colisão":[],"Tempo de Execução":360,"Velocidade":0.4499999999999993},"URU4O56":{"Aceleração":0.003699448529411717,"Acima da Velocidade":false,"Batido":false,"Posicao":[385.0,455.99999999999994],"Posição Prevista":2934.705882352918,"Risco Colisão":[],"Tempo de Execução":360,"Velocidade":0.8062499999999986}},"4211":{"URU2Y34":{"Aceleração":-0.0001953125000000444,"Acima da Velocidade":false,"Batido":false,"Posicao":[745.0,362.65000000000083],"Posição Prevista":701.649999999979,"Risco Colisão":[],"Tempo de Execução":360,"Velocidade":0.4468749999999986},"URU4O56":{"Aceleração":0.0007812499999999556,"Acima da Velocidade":false,"Batido":false,"Posicao":[385.0,469.0999999999999],"Posição Prevista":1615.0999999999774,"Risco Colisão":[],"Tempo de Execução":360,"Velocidade":0.8187499999999979}},"4227":{"URU2Y34":{"Aceleração":-0.0001953125000000444,"Acima da Velocidade":false,"Batido":false,"Posicao":[745.0,355.55000000000086],"Posição Prevista":691.5499999999784,"Risco Colisão":[],"Tempo de Execução":360,"Velocidade":0.44374999999999787},"URU4O56":{"Aceleração":0.0007812500000001776,"Acima da Velocidade":false,"Batido":false,"Posicao":[385.0,482.3999999999999],"Posição Prevista":1640.4000000000824,"Risco Colisão":[],"Tempo de Execução":360,"Velocidade":0.8312500000000007}},"4243":{"URU2Y34":{"Aceleração":-0.0001953125000000444,"Acima da Velocidade":false,"Batido":false,"Posicao":[745.0,348.5000000000009],"Posição Prevista":681.4999999999777,"Risco Colisão":[],"Tempo de Execução":360,"Velocidade":0.44062499999999716},"URU4O56":{"Aceleração":0.0007812499999999556,"Acima da Velocidade":false,"Batido":false,"Posicao":[385.0,495.8999999999999],"Posição Prevista":1665.8999999999794,"Risco Colisão":[],"Tempo de Execução":360,"Velocidade":0.84375}},"4259":{"URU2Y34":{"Aceleração":-0.00019531249999982236,"Acima da Velocidade":false,"Batido":false,"Posicao":[745.0,341.5000000000009],"Posição Prevista":671.5000000000828,"Risco Colisão":[],"Tempo de Execução":361,"Velocidade":0.4375},"URU4O56":{"Aceleração":0.0007812499999999556,"Acima da Velocidade":false,"Batido":false,"Posicao":[385.0,509.5999999999999],"Posição Prevista":1691.5999999999788,"Risco Colisão":[],"Tempo de Execução":361,"Velocidade":0.8562499999999993}},"4275":{"URU2Y34":{"Aceleração":-0.0001953125000000444,"Acima da Velocidade":false,"Batido":false,"Posicao":[745.0,334.5500000000009],"Posição Prevista":661.5499999999797,"Risco Colisão":[],"Tempo de Execução":361,"Velocidade":0.4343749999999993},"URU4O56":{"Aceleração":0.0007812499999999556,"Acima da Velocidade":false,"Batido":false,"Posicao":[385.0,523.4999999999999],"Posição Prevista":1717.4999999999782,"Risco Colisão":[],"Tempo de Execução":361,"Velocidade":0.8687499999999986}},"4291":{"URU2Y34":{"Aceleração":-0.0001953125000000444,"Acima da Velocidade":false,"Batido":false,"Posicao":[745.0,327.65000000000094],"Posição Prevista":651.6499999999792,"Risco Colisão":[],"Tempo de Execução":361,"Velocidade":0.4312499999999986},"URU4O56":{"Aceleração":0.0007812500000001776,"Acima da Velocidade":false,"Batido":false,"Posicao":[385.0,537.5999999999999],"Posição Prevista":1743.6000000000831,"Risco Colisão":[],"Tempo de Execução":361,"Velocidade":0.8812500000000014}},"4308":{"URU2Y34":{"Aceleração":-0.001665224913494843,"Acima da Velocidade":false,"Batido":false,"Posicao":[745.0,320.800000000001],"Posição Prevista":-134.45000000001835,"Risco Colisão":[],"Tempo de Execução":361,"Velocidade":0.40294117647058625},"URU4O56":{"Aceleração":-0.002357266435986399,"Acima da Velocidade":false,"Batido":false,"Posicao":[385.0,551.8999999999999],"Posição Prevista":183.6499999998723,"Risco Colisão":[],"Tempo de Execução":361,"Velocidade":0.8411764705882326}},"4324":{"URU2Y34":{"Aceleração":0.0013786764705881818,"Acima da Velocidade":false,"Batido":false,"Posicao":[745.0,314.000000000001],"Posição Prevista":1357.2941176470326,"Risco Colisão":[],"Tempo de Execução":361,"Velocidade":0.42499999999999716},"URU4O56":{"Aceleração":0.00406709558823546,"Acima da Velocidade":false,"Batido":false,"Posicao":[385.0,566.3999999999999],"Posição Prevista":3310.5176470589,"Risco Colisão":[],"Tempo de Execução":361,"Velocidade":0.90625}},"4340":{"URU2Y34":{"Aceleração":-0.00019531249999982236,"Acima da Velocidade":false,"Batido":false,"Posicao":[745.0,307.250000000001],"Posição Prevista":622.2500000000829,"Risco Colisão":[],"Tempo de Execução":361,"Velocidade":0.421875},"URU4O56":{"Aceleração":0.0007812499999997335,"Acima da Velocidade":false,"Batido":false,"Posicao":[385.0,581.0999999999998],"Posição Prevista":1823.099999999873,"Risco Colisão":[],"Tempo de Execução":361,"Velocidade":0.9187499999999957}},"435":{"CHI0G12":{"Aceleração":-0.001016435986159316,"Acima da Velocidade":false,"Batido":false,"Posicao":[565.0,201.60000000000005],"Posição Prevista":158.8499999999234,"Risco Colisão":[],"Tempo de Execução":182,"Velocidade":0.47647058823529376}},"4356":{"URU2Y34":{"Aceleração":-0.0001953125000000444,"Acima da Velocidade":false,"Batido":false,"Posicao":[745.0,300.55000000000103],"Posição Prevista":612.54999999998,"Risco Colisão":[],"Tempo de Execução":362,"Velocidade":0.4187499999999993},"URU4O56":{"Aceleração":0.0007812500000001776,"Acima da Velocidade":false,"Batido":false,"Posicao":[385.0,595.9999999999998],"Posição Prevista":1850.0000000000803,"Risco Colisão":[],"Tempo de Execução":362,"Velocidade":0.9312499999999986}},"4373":{"URU2Y34":{"Aceleração":-0.0016219723183391371,"Acima da Velocidade":false,"Batido":false,"Posicao":[745.0,293.90000000000106],"Posição Prevista":-150.85000000001946,"Risco Colisão":[],"Tempo de Execução":362,"Velocidade":0.39117647058823396},"URU4O56":{"Aceleração":-0.002530276816609229,"Acima da Velocidade":false,"Batido":false,"Posicao":[385.0,611.0999999999997],"Posição Prevista":200.84999999987326,"Risco Colisão":[],"Tempo de Execução":362,"Velocidade":0.8882352941176417}},"4389":{"URU2Y34":{"Aceleração":0.0013327205882352443,"Acima da Velocidade":false,"Batido":false,"Posicao":[745.0,287.3000000000011],"Posição Prevista":1297.4176470587995,"Risco Colisão":[],"Tempo de Execução":362,"Velocidade":0.41249999999999787},"URU4O56":{"Aceleração":0.004250919117647661,"Acima da Velocidade":false,"Batido":false,"Posicao":[385.0,626.3999999999997],"Posição Prevista":3503.223529412046,"Risco Colisão":[],"Tempo de Execução":362,"Velocidade":0.9562500000000043}},"4405":{"URU2Y34":{"Aceleração":-0.0001953125000000444,"Acima da Velocidade":false,"Batido":false,"Posicao":[745.0,280.75000000000114],"Posição Prevista":583.749999999978,"Risco Colisão":[],"Tempo de Execução":362,"Velocidade":0.40937499999999716},"URU4O56":{"Aceleração":0.0007812499999997335,"Acima da Velocidade":false,"Batido":false,"Posicao":[385.0,641.8999999999997],"Posição Prevista":1931.8999999998769,"Risco Colisão":[],"Tempo de Execução":362,"Velocidade":0.96875}},"4421":{"URU2Y34":{"Aceleração":-0.00019531249999982236,"Acima da Velocidade":false,"Batido":false,"Posicao":[745.0,274.25000000000114],"Posição Prevista":574.250000000083,"Risco Colisão":[],"Tempo de Execução":362,"Velocidade":0.40625},"URU4O56":{"Aceleração":0.0007812499999997335,"Acima da Velocidade":false,"Batido":false,"Posicao":[385.0,657.5999999999997],"Posição Prevista":1959.5999999998728,"Risco Colisão":[],"Tempo de Execução":362,"Velocidade":0.9812499999999957}},"4438":{"URU2Y34":{"Aceleração":-0.001578719723183431,"Acima da Velocidade":false,"Batido":false,"Posicao":[745.0,267.80000000000115],"Posição Prevista":-166.4500000000204,"Risco Colisão":[],"Tempo de Execução":362,"Velocidade":0.37941176470588167},"URU4O56":{"Aceleração":-0.002703287197231661,"Acima da Velocidade":false,"Batido":false,"Posicao":[385.0,673.4999999999997],"Posição Prevista":221.250000000088,"Risco Colisão":[],"Tempo de Execução":362,"Velocidade":0.9352941176470575}},"4454":{"URU2Y34":{"Aceleração":0.0012867647058823067,"Acima da Velocidade":false,"Batido":false,"Posicao":[745.0,261.40000000000117],"Posição Prevista":1238.3411764705668,"Risco Colisão":[],"Tempo de Execução":363,"Velocidade":0.3999999999999986},"URU4O56":{"Aceleração":0.004434742647058995,"Acima da Velocidade":false,"Batido":false,"Posicao":[385.0,689.5999999999997],"Posição Prevista":3699.129411764786,"Risco Colisão":[],"Tempo de Execução":363,"Velocidade":1.0062500000000014}},"4470":{"URU2Y34":{"Aceleração":-0.0001953125000000444,"Acima da Velocidade":false,"Batido":false,"Posicao":[745.0,255.0500000000012],"Posição Prevista":546.0499999999787,"Risco Colisão":[],"Tempo de Execução":363,"Velocidade":0.39687499999999787},"URU4O56":{"Aceleração":0.0007812499999997335,"Acima da Velocidade":false,"Batido":false,"Posicao":[385.0,705.8999999999996],"Posição Prevista":2043.8999999998741,"Risco Colisão":[],"Tempo de Execução":363,"Velocidade":1.0187499999999972}},"4486":{"URU2Y34":{"Aceleração":-0.0001953124999999334,"Acima da Velocidade":false,"Batido":false,"Posicao":[745.0,248.75000000000122],"Posição Prevista":536.7500000000309,"Risco Colisão":[],"Tempo de Execução":363,"Velocidade":0.39374999999999893},"URU4O56":{"Aceleração":0.0007812500000001776,"Acima da Velocidade":false,"Batido":false,"Posicao":[385.0,722.3999999999996],"Posição Prevista":2072.4000000000815,"Risco Colisão":[],"Tempo de Execução":363,"Velocidade":1.03125}},"4503":{"URU2Y34":{"Aceleração":-0.0015354671280277186,"Acima da Velocidade":false,"Batido":false,"Posicao":[745.0,242.50000000000125],"Posição Prevista":-181.25000000001967,"Risco Colisão":[],"Tempo de Execução":363,"Velocidade":0.3676470588235277},"URU4O56":{"Aceleração":-0.002876297577854909,"Acima da Velocidade":false,"Batido":false,"Posicao":[385.0,739.0999999999996],"Posição Prevista":244.84999999987167,"Risco Colisão":[],"Tempo de Execução":363,"Velocidade":0.9823529411764665}},"451":{"CHI0G12":{"Aceleração":0.0026424632352940736,"Acima da Velocidade":false,"Batido":false,"Posicao":[565.0,209.90000000000003],"Posição Prevista":1925.547058823508,"Risco Colisão":[],"Tempo de Execução":182,"Velocidade":0.5187499999999989}},"4519":{"URU2Y34":{"Aceleração":0.0012408088235294733,"Acima da Velocidade":false,"Batido":false,"Posicao":[745.0,236.30000000000126],"Posição Prevista":1180.064705882382,"Risco Colisão":[],"Tempo de Execução":363,"Velocidade":0.3874999999999993},"URU4O56":{"Aceleração":0.004618566176470752,"Acima da Velocidade":false,"Batido":false,"Posicao":[385.0,755.9999999999995],"Posição Prevista":3898.235294117721,"Risco Colisão":[],"Tempo de Execução":363,"Velocidade":1.0562499999999986}},"4535":{"URU2Y34":{"Aceleração":-0.0001953125000000444,"Acima da Velocidade":false,"Batido":false,"Posicao":[745.0,230.15000000000128],"Posição Prevista":509.1499999999794,"Risco Colisão":[],"Tempo de Execução":363,"Velocidade":0.3843749999999986},"URU4O56":{"Aceleração":0.0007812500000001776,"Acima da Velocidade":false,"Batido":false,"Posicao":[385.0,773.0999999999996],"Posição Prevista":2159.1000000000827,"Risco Colisão":[],"Tempo de Execução":363,"Velocidade":1.0687500000000014}},"4551":{"URU2Y34":{"Aceleração":-0.0001953125000000444,"Acima da Velocidade":false,"Batido":false,"Posicao":[745.0,224.05000000000132],"Posição Prevista":500.0499999999788,"Risco Colisão":[],"Tempo de Execução":363,"Velocidade":0.38124999999999787},"URU4O56":{"Aceleração":0.0007812499999997335,"Acima da Velocidade":false,"Batido":false,"Posicao":[385.0,790.3999999999995],"Posição Prevista":2188.399999999874,"Risco Colisão":[],"Tempo de Execução":363,"Velocidade":1.0812499999999972}},"4567":{"URU2Y34":{"Aceleração":-0.00019531249999982236,"Acima da Velocidade":false,"Batido":false,"Posicao":[745.0,218.0000000000013],"Posição Prevista":491.0000000000839,"Risco Colisão":[],"Tempo de Execução":364,"Velocidade":0.3781250000000007},"URU4O56":{"Aceleração":0.0007812500000001776,"Acima da Velocidade":false,"Batido":false,"Posicao":[385.0,807.8999999999995],"Posição Prevista":2217.9000000000815,"Risco Colisão":[],"Tempo de Execução":364,"Velocidade":1.09375}},"4583":{"URU2Y34":{"Aceleração":-0.00019531250000015543,"Acima da Velocidade":false,"Batido":false,"Posicao":[745.0,212.00000000000134],"Posição Prevista":481.99999999992804,"Risco Colisão":[],"Tempo de Execução":364,"Velocidade":0.3749999999999982},"URU4O56":{"Aceleração":0.0007812499999997335,"Acima da Velocidade":false,"Batido":false,"Posicao":[385.0,825.5999999999995],"Posição Prevista":2247.5999999998726,"Risco Colisão":[],"Tempo de Execução":364,"Velocidade":1.1062499999999957}},"4600":{"PAR7P89":null,"URU2Y34":{"Aceleração":-0.0014705882352941517,"Acima da Velocidade":false,"Batido":false,"Posicao":[745.0,206.05000000000138],"Posição Prevista":-201.9500000000187,"Risco Colisão":[],"Tempo de Execução":364,"Velocidade":0.34999999999999765},"URU4O56":{"Aceleração":-0.003135813148788753,"Acima da Velocidade":false,"Batido":false,"Posicao":[385.0,843.4999999999994],"Posição Prevista":286.2500000000889,"Risco Colisão":[],"Tempo de Execução":364,"Velocidade":1.052941176470587}},"4616":{"PAR7P89":{"Batido":false,"Posicao":[655.0,863],"Posição Prevista":863.0,"Risco Colisão":[],"Tempo de Execução":416},"URU2Y34":{"Aceleração":0.0011718750000000583,"Acima da Velocidade":false,"Batido":false,"Posicao":[745.0,200.1500000000014],"Posição Prevista":1094.150000000027,"Risco Colisão":[],"Tempo de Execução":416,"Velocidade":0.3687499999999986},"URU4O56":{"Aceleração":0.004894301470588405,"Acima da Velocidade":false,"Batido":false,"Posicao":[385.0,861.5999999999995],"Posição Prevista":4202.894117647138,"Risco Colisão":[],"Tempo de Execução":416,"Velocidade":1.1312500000000014}},"4632":{"PAR7P89":{"Acima da Velocidade":false,"Batido":false,"Posicao":[655.0,856],"Posição Prevista":1276.0,"Risco Colisão":[],"Tempo de Execução":416,"Velocidade":0.4375},"URU2Y34":{"Aceleração":-0.0001953124999999334,"Acima da Velocidade":false,"Batido":false,"Posicao":[745.0,194.3000000000014],"Posição Prevista":455.3000000000318,"Risco Colisão":[],"Tempo de Execução":416,"Velocidade":0.36562499999999964},"URU4O56":{"Aceleração":0.0007812499999997335,"Acima da Velocidade":false,"Batido":false,"Posicao":[385.0,879.8999999999994],"Posição Prevista":2337.899999999874,"Risco Colisão":[],"Tempo de Execução":416,"Velocidade":1.1437499999999972}},"4649":{"PAR7P89":{"Aceleração":-0.001686851211072508,"Acima da Velocidade":false,"Batido":false,"Posicao":[655.0,849.05],"Posição Prevista":388.55000000008397,"Risco Colisão":[],"Tempo de Execução":416,"Velocidade":0.40882352941176736},"URU2Y34":{"Aceleração":-0.001438148788927373,"Acima da Velocidade":false,"Batido":false,"Posicao":[745.0,188.50000000000142],"Posição Prevista":-211.62500000001899,"Risco Colisão":[],"Tempo de Execução":417,"Velocidade":0.3411764705882343},"URU4O56":{"Aceleração":-0.0032655709342558938,"Acima da Velocidade":false,"Batido":false,"Posicao":[385.0,898.3999999999994],"Posição Prevista":309.65000000008354,"Risco Colisão":[],"Tempo de Execução":417,"Velocidade":1.088235294117647}},"4665":{"PAR7P89":{"Aceleração":0.001401654411764451,"Acima da Velocidade":false,"Batido":false,"Posicao":[655.0,842.15],"Posição Prevista":1902.0323529410578,"Risco Colisão":[],"Tempo de Execução":417,"Velocidade":0.4312499999999986},"URU2Y34":{"Aceleração":0.001137408088235356,"Acima da Velocidade":false,"Batido":false,"Posicao":[745.0,182.75000000000142],"Posição Prevista":1051.8676470588534,"Risco Colisão":[],"Tempo de Execução":417,"Velocidade":0.359375},"URU4O56":{"Aceleração":0.005032169117646798,"Acima da Velocidade":false,"Batido":false,"Posicao":[385.0,917.0999999999993],"Posição Prevista":4357.92352941164,"Risco Colisão":[],"Tempo de Execução":417,"Velocidade":1.1687499999999957}},"468":{"CHI0G12":{"Aceleração":-0.0011029411764705256,"Acima da Velocidade":false,"Batido":false,"Posicao":[565.0,218.40000000000003],"Posição Prevista":154.65000000003272,"Risco Colisão":[],"Tempo de Execução":182,"Velocidade":0.5}},"4681":{"PAR7P89":{"Aceleração":-0.00019531249999982236,"Acima da Velocidade":false,"Batido":false,"Posicao":[655.0,835.3],"Posição Prevista":1156.3000000000832,"Risco Colisão":[],"Tempo de Execução":417,"Velocidade":0.4281250000000014},"URU2Y34":{"Aceleração":-0.00019531250000015543,"Acima da Velocidade":false,"Batido":false,"Posicao":[745.0,177.05000000000146],"Posição Prevista":429.0499999999274,"Risco Colisão":[],"Tempo de Execução":417,"Velocidade":0.3562499999999975},"URU4O56":{"Aceleração":0.0007812500000001776,"Acima da Velocidade":false,"Batido":false,"Posicao":[385.0,935.9999999999993],"Posição Prevista":2430.00000000008,"Risco Colisão":[],"Tempo de Execução":418,"Velocidade":1.1812499999999986}},"4697":{"PAR7P89":null,"URU2Y34":{"Aceleração":-0.0001953124999999334,"Acima da Velocidade":false,"Batido":false,"Posicao":[745.0,171.40000000000148],"Posição Prevista":420.4000000000308,"Risco Colisão":[],"Tempo de Execução":418,"Velocidade":0.3531249999999986},"URU4O56":{"Aceleração":0.0007812499999997335,"Acima da Velocidade":false,"Batido":false,"Posicao":[385.0,955.0999999999992],"Posição Prevista":2461.099999999871,"Risco Colisão":[],"Tempo de Execução":418,"Velocidade":1.1937499999999943}},"4713":{"PAR7P89":{"Batido":false,"Posicao":[655.0,828.5],"Posição Prevista":828.5,"Risco Colisão":[],"Tempo de Execução":418},"URU2Y34":{"Aceleração":-0.0001953124999999334,"Acima da Velocidade":false,"Batido":false,"Posicao":[745.0,165.8000000000015],"Posição Prevista":411.80000000003184,"Risco Colisão":[],"Tempo de Execução":418,"Velocidade":0.34999999999999964}},"4729":{"PAR7P89":{"Acima da Velocidade":false,"Batido":false,"Posicao":[655.0,821.75],"Posição Prevista":1226.75,"Risco Colisão":[],"Tempo de Execução":418,"Velocidade":0.421875},"URU2Y34":{"Aceleração":-0.00019531250000015543,"Acima da Velocidade":false,"Batido":false,"Posicao":[745.0,160.25000000000153],"Posição Prevista":403.2499999999272,"Risco Colisão":[],"Tempo de Execução":418,"Velocidade":0.34687499999999716}},"4745":{"PAR7P89":{"Aceleração":-0.00019531249999982236,"Acima da Velocidade":false,"Batido":false,"Posicao":[655.0,815.05],"Posição Prevista":1127.0500000000845,"Risco Colisão":[],"Tempo de Execução":418,"Velocidade":0.41875000000000284},"URU2Y34":{"Aceleração":-0.00019531249999982236,"Acima da Velocidade":false,"Batido":false,"Posicao":[745.0,154.75000000000153],"Posição Prevista":394.7500000000834,"Risco Colisão":[],"Tempo de Execução":418,"Velocidade":0.34375}},"4761":{"PAR7P89":{"Aceleração":-0.00019531250000026645,"Acima da Velocidade":false,"Batido":false,"Posicao":[655.0,808.4],"Posição Prevista":1117.399999999876,"Risco Colisão":[],"Tempo de Execução":419,"Velocidade":0.4156249999999986},"URU2Y34":{"Aceleração":-0.0001953125000000444,"Acima da Velocidade":false,"Batido":false,"Posicao":[745.0,149.30000000000155],"Posição Prevista":386.2999999999804,"Risco Colisão":[],"Tempo de Execução":419,"Velocidade":0.3406249999999993}},"4778":{"PAR7P89":{"Aceleração":-0.0016111591695500106,"Acima da Velocidade":false,"Batido":false,"Posicao":[655.0,801.8],"Posição Prevista":359.6750000000858,"Risco Colisão":[],"Tempo de Execução":419,"Velocidade":0.3882352941176484},"URU2Y34":{"Aceleração":-0.0013516435986159546,"Acima da Velocidade":false,"Batido":false,"Posicao":[745.0,143.90000000000157],"Posição Prevista":-235.22500000001935,"Risco Colisão":[],"Tempo de Execução":419,"Velocidade":0.31764705882352806}},"4794":{"PAR7P89":{"Aceleração":0.0013212316176467974,"Acima da Velocidade":false,"Batido":false,"Posicao":[655.0,795.25],"Posição Prevista":1797.0735294116416,"Risco Colisão":[],"Tempo de Execução":419,"Velocidade":0.40937499999999716},"URU2Y34":{"Aceleração":0.001045496323529363,"Acima da Velocidade":false,"Batido":false,"Posicao":[745.0,138.5500000000016],"Posição Prevista":941.3147058823299,"Risco Colisão":[],"Tempo de Execução":419,"Velocidade":0.33437499999999787}},"4811":{"PAR7P89":{"Aceleração":-0.0015895328719721527,"Acima da Velocidade":false,"Batido":false,"Posicao":[655.0,788.75],"Posição Prevista":351.8750000000862,"Risco Colisão":[],"Tempo de Execução":419,"Velocidade":0.38235294117647056},"URU2Y34":{"Aceleração":-0.0013300173010379955,"Acima da Velocidade":false,"Batido":false,"Posicao":[745.0,133.25000000000162],"Posição Prevista":-240.62499999996464,"Risco Colisão":[],"Tempo de Execução":419,"Velocidade":0.31176470588235194}},"4827":{"BRA6W78":null,"PAR7P89":{"Aceleração":0.0012982536764707675,"Acima da Velocidade":false,"Batido":false,"Posicao":[655.0,782.3],"Posição Prevista":1767.5352941177323,"Risco Colisão":[],"Tempo de Execução":419,"Velocidade":0.40312500000000284},"URU2Y34":{"Aceleração":0.0010225183823530035,"Acima da Velocidade":false,"Batido":false,"Posicao":[745.0,128.00000000000162],"Posição Prevista":914.1764705882656,"Risco Colisão":[],"Tempo de Execução":419,"Velocidade":0.328125}},"484":{"CHI0G12":{"Aceleração":0.0027343750000000666,"Acima da Velocidade":false,"Batido":false,"Posicao":[565.0,227.10000000000005],"Posição Prevista":2009.1000000000317,"Risco Colisão":[],"Tempo de Execução":182,"Velocidade":0.5437500000000011}},"4843":{"BRA6W78":{"Batido":false,"Posicao":[745.0,867],"Posição Prevista":867.0,"Risco Colisão":[],"Tempo de Execução":468},"PAR7P89":{"Aceleração":-0.00019531250000026645,"Acima da Velocidade":false,"Batido":false,"Posicao":[655.0,775.9],"Posição Prevista":1069.899999999876,"Risco Colisão":[],"Tempo de Execução":468,"Velocidade":0.3999999999999986},"URU2Y34":{"Aceleração":-0.00019531250000009992,"Acima da Velocidade":false,"Batido":false,"Posicao":[745.0,122.80000000000165],"Posição Prevista":344.7999999999541,"Risco Colisão":[],"Tempo de Execução":468,"Velocidade":0.3249999999999984}},"4859":{"BRA6W78":{"Acima da Velocidade":false,"Batido":false,"Posicao":[745.0,864],"Posição Prevista":1044.0,"Risco Colisão":[],"Tempo de Execução":468,"Velocidade":0.1875},"PAR7P89":{"Aceleração":-0.00019531249999982236,"Acima da Velocidade":false,"Batido":false,"Posicao":[655.0,769.55],"Posição Prevista":1060.5500000000832,"Risco Colisão":[],"Tempo de Execução":468,"Velocidade":0.3968750000000014},"URU2Y34":{"Aceleração":-0.0001953124999999889,"Acima da Velocidade":false,"Batido":false,"Posicao":[745.0,117.65000000000167],"Posição Prevista":336.65000000000543,"Risco Colisão":[],"Tempo de Execução":469,"Velocidade":0.3218749999999986}},"4875":{"BRA6W78":{"Aceleração":0.0,"Acima da Velocidade":false,"Batido":false,"Posicao":[745.0,861],"Posição Prevista":1041.0,"Risco Colisão":[],"Tempo de Execução":469,"Velocidade":0.1875},"PAR7P89":{"Aceleração":-0.00019531250000026645,"Acima da Velocidade":false,"Batido":false,"Posicao":[655.0,763.25],"Posição Prevista":1051.2499999998745,"Risco Colisão":[],"Tempo de Execução":469,"Velocidade":0.39374999999999716},"URU2Y34":{"Aceleração":-0.0001953124999999889,"Acima da Velocidade":false,"Batido":false,"Posicao":[745.0,112.55000000000169],"Posição Prevista":328.55000000000564,"Risco Colisão":[],"Tempo de Execução":469,"Velocidade":0.31874999999999876}},"4891":{"BRA6W78":{"Aceleração":0.0,"Acima da Velocidade":false,"Batido":false,"Posicao":[745.0,858],"Posição Prevista":1038.0,"Risco Colisão":[],"Tempo de Execução":469,"Velocidade":0.1875},"PAR7P89":{"Aceleração":-0.00019531249999982236,"Acima da Velocidade":false,"Batido":false,"Posicao":[655.0,757.0],"Posição Prevista":1042.0000000000819,"Risco Colisão":[],"Tempo de Execução":469,"Velocidade":0.390625},"URU2Y34":{"Aceleração":-0.0001953124999999889,"Acima da Velocidade":false,"Batido":false,"Posicao":[745.0,107.5000000000017],"Posição Prevista":320.5000000000058,"Risco Colisão":[],"Tempo de Execução":469,"Velocidade":0.31562499999999893}},"49":{"CHI0G12":{"Aceleração":2.1626297577839902e-05,"Acima da Velocidade":false,"Batido":false,"Posicao":[565.0,62.4],"Posição Prevista":271.64999999999213,"Risco Colisão":[],"Tempo de Execução":179,"Velocidade":0.19411764705882337}},"4907":{"BRA6W78":{"Aceleração":-0.01171875,"Acima da Velocidade":false,"Batido":true,"Posicao":[655.0,858],"Posição Prevista":-4542.0,"Risco Colisão":["PAR7P89"],"Tempo de Execução":469,"Velocidade":0.0},"PAR7P89":{"Aceleração":-0.00019531249999982236,"Acima da Velocidade":false,"Batido":false,"Posicao":[655.0,750.8],"Posição Prevista":1032.8000000000845,"Risco Colisão":["BRA6W78"],"Tempo de Execução":469,"Velocidade":0.38750000000000284},"URU2Y34":{"Aceleração":-0.0001953124999999889,"Acima da Velocidade":false,"Batido":false,"Posicao":[745.0,102.50000000000172],"Posição Prevista":312.50000000000597,"Risco Colisão":[],"Tempo de Execução":469,"Velocidade":0.3124999999999991}},"4923":{"BRA6W78":{"Aceleração":0.01171875,"Acima da Velocidade":false,"Batido":false,"Posicao":[655.0,855],"Posição Prevista":6435.0,"Risco Colisão":[],"Tempo de Execução":469,"Velocidade":0.1875},"PAR7P89":{"Aceleração":-0.00019531250000026645,"Acima da Velocidade":false,"Batido":false,"Posicao":[655.0,744.65],"Posição Prevista":1023.649999999876,"Risco Colisão":[],"Tempo de Execução":470,"Velocidade":0.3843749999999986},"URU2Y34":{"Aceleração":-0.0001953124999999889,"Acima da Velocidade":false,"Batido":false,"Posicao":[745.0,97.55000000000173],"Posição Prevista":304.55000000000615,"Risco Colisão":[],"Tempo de Execução":470,"Velocidade":0.3093749999999993}},"4940":{"BRA6W78":{"Aceleração":-0.0006487889273356395,"Acima da Velocidade":false,"Batido":false,"Posicao":[655.0,852],"Posição Prevista":694.5000000000003,"Risco Colisão":[],"Tempo de Execução":470,"Velocidade":0.17647058823529413},"PAR7P89":{"Aceleração":-0.0015030276816607375,"Acima da Velocidade":false,"Batido":false,"Posicao":[655.0,738.55],"Posição Prevista":322.6750000000857,"Risco Colisão":[],"Tempo de Execução":470,"Velocidade":0.35882352941176604},"URU2Y34":{"Aceleração":-0.0012435121107266817,"Acima da Velocidade":false,"Batido":false,"Posicao":[745.0,92.65000000000175],"Posição Prevista":-260.2250000000194,"Risco Colisão":[],"Tempo de Execução":470,"Velocidade":0.2882352941176457}},"4956":{"BRA6W78":{"Aceleração":0.0006893382352941169,"Acima da Velocidade":false,"Batido":false,"Posicao":[655.0,849],"Posição Prevista":1346.647058823529,"Risco Colisão":["PAR7P89"],"Tempo de Execução":470,"Velocidade":0.1875},"PAR7P89":{"Aceleração":0.0012063419117644449,"Acima da Velocidade":false,"Batido":false,"Posicao":[655.0,732.5],"Posição Prevista":1651.3823529410533,"Risco Colisão":["BRA6W78"],"Tempo de Execução":470,"Velocidade":0.37812499999999716},"URU2Y34":{"Aceleração":0.0009306066176470659,"Acima da Velocidade":false,"Batido":false,"Posicao":[745.0,87.80000000000177],"Posição Prevista":807.6235294117686,"Risco Colisão":[],"Tempo de Execução":470,"Velocidade":0.30312499999999876}},"4972":{"BRA6W78":{"Aceleração":0.0,"Acima da Velocidade":false,"Batido":false,"Posicao":[655.0,846],"Posição Prevista":1026.0,"Risco Colisão":["PAR7P89"],"Tempo de Execução":471,"Velocidade":0.1875},"PAR7P89":{"Aceleração":-0.00019531249999982236,"Acima da Velocidade":false,"Batido":false,"Posicao":[655.0,726.5],"Posição Prevista":996.5000000000819,"Risco Colisão":["BRA6W78"],"Tempo de Execução":471,"Velocidade":0.375},"URU2Y34":{"Aceleração":-0.0001953124999999889,"Acima da Velocidade":false,"Batido":false,"Posicao":[745.0,83.00000000000179],"Posição Prevista":281.0000000000059,"Risco Colisão":[],"Tempo de Execução":471,"Velocidade":0.29999999999999893}},"4989":{"BRA6W78":{"Aceleração":-0.0006487889273356395,"Acima da Velocidade":false,"Batido":false,"Posicao":[655.0,843],"Posição Prevista":685.5000000000003,"Risco Colisão":[],"Tempo de Execução":471,"Velocidade":0.17647058823529413},"PAR7P89":{"Aceleração":-0.001470588235293959,"Acima da Velocidade":false,"Batido":false,"Posicao":[655.0,720.55],"Posição Prevista":312.5500000000852,"Risco Colisão":[],"Tempo de Execução":471,"Velocidade":0.3500000000000027},"URU2Y34":{"Aceleração":-0.0012110726643597986,"Acima da Velocidade":false,"Batido":false,"Posicao":[745.0,78.25000000000179],"Posição Prevista":-266.74999999996544,"Risco Colisão":[],"Tempo de Execução":471,"Velocidade":0.27941176470588236}},"500":{"CHI0G12":{"Aceleração":0.0007812499999999556,"Acima da Velocidade":false,"Batido":false,"Posicao":[565.0,236.00000000000006],"Posição Prevista":1129.99999999998,"Risco Colisão":[],"Tempo de Execução":182,"Velocidade":0.5562500000000004}},"516":{"CHI0G12":{"Aceleração":0.0007812499999999556,"Acima da Velocidade":false,"Batido":false,"Posicao":[565.0,245.10000000000005],"Posição Prevista":1151.0999999999792,"Risco Colisão":[],"Tempo de Execução":182,"Velocidade":0.5687499999999996}},"532":{"CHI0G12":{"Aceleração":0.0007812500000000666,"Acima da Velocidade":false,"Batido":false,"Posicao":[565.0,254.40000000000006],"Posição Prevista":1172.4000000000315,"Risco Colisão":[],"Tempo de Execução":182,"Velocidade":0.5812500000000007}},"548":{"CHI0G12":{"Aceleração":0.0007812500000000666,"Acima da Velocidade":false,"Batido":false,"Posicao":[565.0,263.9000000000001],"Posição Prevista":1193.9000000000324,"Risco Colisão":[],"Tempo de Execução":182,"Velocidade":0.5937500000000018}},"564":{"CHI0G12":{"Aceleração":0.0007812499999996225,"Acima da Velocidade":false,"Batido":false,"Posicao":[565.0,273.6],"Posição Prevista":1215.599999999822,"Risco Colisão":[],"Tempo de Execução":182,"Velocidade":0.6062499999999957}},"580":{"CHI0G12":{"Aceleração":0.0007812500000003997,"Acima da Velocidade":false,"Batido":false,"Posicao":[565.0,283.50000000000006],"Posição Prevista":1237.5000000001862,"Risco Colisão":[],"Tempo de Execução":182,"Velocidade":0.6187500000000021}},"596":{"CHI0G12":{"Aceleração":0.0007812499999997335,"Acima da Velocidade":false,"Batido":false,"Posicao":[565.0,293.6],"Posição Prevista":1259.5999999998753,"Risco Colisão":[],"Tempo de Execução":183,"Velocidade":0.6312499999999979}},"612":{"CHI0G12":{"Aceleração":0.0007812500000001776,"Acima da Velocidade":false,"Batido":false,"Posicao":[565.0,303.90000000000003],"Posição Prevista":1281.9000000000826,"Risco Colisão":[],"Tempo de Execução":183,"Velocidade":0.6437500000000007}},"629":{"CHI0G12":{"Aceleração":-0.0015354671280277219,"Acima da Velocidade":false,"Batido":false,"Posicao":[565.0,314.40000000000003],"Posição Prevista":145.64999999997917,"Risco Colisão":[],"Tempo de Execução":183,"Velocidade":0.6176470588235294}},"645":{"CHI0G12":{"Aceleração":0.0031939338235293657,"Acima da Velocidade":false,"Batido":false,"Posicao":[565.0,325.1],"Posição Prevista":2438.8647058823312,"Risco Colisão":[],"Tempo de Execução":183,"Velocidade":0.6687499999999993}},"65":{"CHI0G12":{"Aceleração":0.0015395220588235673,"Acima da Velocidade":false,"Batido":false,"Posicao":[565.0,65.9],"Posição Prevista":985.3117647059003,"Risco Colisão":[],"Tempo de Execução":179,"Velocidade":0.21875000000000044}},"661":{"CHI0G12":{"Aceleração":0.0007812499999999556,"Acima da Velocidade":false,"Batido":false,"Posicao":[565.0,336.0],"Posição Prevista":1349.9999999999782,"Risco Colisão":[],"Tempo de Execução":183,"Velocidade":0.6812499999999986}},"678":{"CHI0G12":{"Aceleração":-0.001665224913494647,"Acima da Velocidade":false,"Batido":false,"Posicao":[565.0,347.1],"Posição Prevista":146.85000000008597,"Risco Colisão":[],"Tempo de Execução":183,"Velocidade":0.6529411764705896}},"694":{"CHI0G12":{"Aceleração":0.0033318014705881957,"Acima da Velocidade":false,"Batido":false,"Posicao":[565.0,358.40000000000003],"Posição Prevista":2571.6941176470414,"Risco Colisão":[],"Tempo de Execução":183,"Velocidade":0.7062500000000007}},"710":{"CHI0G12":{"Aceleração":0.0007812499999999556,"Acima da Velocidade":false,"Batido":false,"Posicao":[565.0,369.90000000000003],"Posição Prevista":1419.8999999999796,"Risco Colisão":[],"Tempo de Execução":183,"Velocidade":0.71875}},"727":{"CHI0G12":{"Aceleração":-0.0017949826989619771,"Acima da Velocidade":false,"Batido":false,"Posicao":[565.0,381.6],"Posição Prevista":149.849999999979,"Risco Colisão":[],"Tempo de Execução":183,"Velocidade":0.6882352941176464}},"743":{"CHI0G12":{"Aceleração":0.003469669117647012,"Acima da Velocidade":false,"Batido":false,"Posicao":[565.0,393.5],"Posição Prevista":2706.3235294117417,"Risco Colisão":[],"Tempo de Execução":184,"Velocidade":0.7437499999999986}},"759":{"CHI0G12":{"Aceleração":0.0007812499999999556,"Acima da Velocidade":false,"Batido":false,"Posicao":[565.0,405.59999999999997],"Posição Prevista":1491.5999999999774,"Risco Colisão":[],"Tempo de Execução":184,"Velocidade":0.7562499999999979}},"776":{"CHI0G12":{"Aceleração":-0.0019247404844289022,"Acima da Velocidade":false,"Batido":false,"Posicao":[565.0,417.9],"Posição Prevista":154.65000000008558,"Risco Colisão":[],"Tempo de Execução":184,"Velocidade":0.7235294117647065}},"792":{"CHI0G12":{"Aceleração":0.0036075367647058418,"Acima da Velocidade":false,"Batido":false,"Posicao":[565.0,430.4],"Posição Prevista":2842.7529411764517,"Risco Colisão":[],"Tempo de Execução":184,"Velocidade":0.78125}},"808":{"CHI0G12":{"Aceleração":0.0007812499999999556,"Acima da Velocidade":false,"Batido":false,"Posicao":[565.0,443.09999999999997],"Posição Prevista":1565.0999999999788,"Risco Colisão":[],"Tempo de Execução":185,"Velocidade":0.7937499999999993}},"81":{"CHI0G12":{"Aceleração":0.0007812499999999278,"Acima da Velocidade":false,"Batido":false,"Posicao":[565.0,69.6],"Posição Prevista":651.599999999966,"Risco Colisão":[],"Tempo de Execução":179,"Velocidade":0.2312499999999993}},"824":{"CHI0G12":{"Aceleração":0.0007812499999999556,"Acima da Velocidade":false,"Batido":false,"Posicao":[565.0,455.99999999999994],"Posição Prevista":1589.9999999999782,"Risco Colisão":[],"Tempo de Execução":185,"Velocidade":0.8062499999999986}},"840":{"CHI0G12":{"Aceleração":0.0007812499999999556,"Acima da Velocidade":false,"Batido":false,"Posicao":[565.0,469.0999999999999],"Posição Prevista":1615.0999999999774,"Risco Colisão":[],"Tempo de Execução":185,"Velocidade":0.8187499999999979}},"857":{"CHI0G12":{"Aceleração":-0.002141003460207448,"Acima da Velocidade":false,"Batido":false,"Posicao":[565.0,482.3999999999999],"Posição Prevista":166.65000000008604,"Risco Colisão":[],"Tempo de Execução":185,"Velocidade":0.7823529411764713}},"873":{"CHI0G12":{"Aceleração":0.003837316176470547,"Acima da Velocidade":false,"Batido":false,"Posicao":[565.0,495.8999999999999],"Posição Prevista":3074.135294117628,"Risco Colisão":[],"Tempo de Execução":185,"Velocidade":0.84375}},"889":{"CHI0G12":{"Aceleração":0.0007812499999999556,"Acima da Velocidade":false,"Batido":false,"Posicao":[565.0,509.5999999999999],"Posição Prevista":1691.5999999999788,"Risco Colisão":[],"Tempo de Execução":185,"Velocidade":0.8562499999999993}},"905":{"CHI0G12":{"Aceleração":0.0007812499999999556,"Acima da Velocidade":false,"Batido":false,"Posicao":[565.0,523.4999999999999],"Posição Prevista":1717.4999999999782,"Risco Colisão":[],"Tempo de Execução":186,"Velocidade":0.8687499999999986}},"921":{"CHI0G12":{"Aceleração":0.0007812500000001776,"Acima da Velocidade":false,"Batido":false,"Posicao":[565.0,537.5999999999999],"Posição Prevista":1743.6000000000831,"Risco Colisão":[],"Tempo de Execução":186,"Velocidade":0.8812500000000014}},"938":{"CHI0G12":{"Aceleração":-0.002357266435986399,"Acima da Velocidade":false,"Batido":false,"Posicao":[565.0,551.8999999999999],"Posição Prevista":183.6499999998723,"Risco Colisão":[],"Tempo de Execução":186,"Velocidade":0.8411764705882326}},"954":{"CHI0G12":{"Aceleração":0.00406709558823546,"Acima da Velocidade":false,"Batido":false,"Posicao":[565.0,566.3999999999999],"Posição Prevista":3310.5176470589,"Risco Colisão":[],"Tempo de Execução":186,"Velocidade":0.90625}},"97":{"CHI0G12":{"Aceleração":0.0007812500000000666,"Acima da Velocidade":false,"Batido":false,"Posicao":[565.0,73.5],"Posição Prevista":667.500000000031,"Risco Colisão":[],"Tempo de Execução":179,"Velocidade":0.24375000000000036}},"970":{"CHI0G12":{"Aceleração":0.0007812499999997335,"Acima da Velocidade":false,"Batido":false,"Posicao":[565.0,581.0999999999998],"Posição Prevista":1823.099999999873,"Risco Colisão":[],"Tempo de Execução":186,"Velocidade":0.9187499999999957}},"986":{"CHI0G12":{"Aceleração":0.0007812500000001776,"Acima da Velocidade":false,"Batido":false,"Posicao":[565.0,595.9999999999998],"Posição Prevista":1850.0000000000803,"Risco Colisão":[],"Tempo de Execução":186,"Velocidade":0.9312499999999986}}},"api":{"BRA6W78":{"ano":"1998","modelo":"Fiat","nome":"Mariana","placa":"BRA6W78"},"CHI0G12":{"ano":"1982","modelo":"Gol","nome":"Gabriel","placa":"CHI0G12"},"PAR7P89":{"ano":"1992","modelo":"Gol","nome":"Paola","placa":"PAR7P89"},"URU2Y34":{"ano":"2000","modelo":"Volkswagen","nome":"Amanda","placa":"URU2Y34"},"URU4O56":{"ano":"2001","modelo":"Celta","nome":"Otavio","placa":"URU4O56"},"URU6M78":{"ano":"1988","modelo":"Volkswagen","nome":"Vinicius","placa":"URU6M78"}}}